{"cd_mun": 5202809, "nm_mun": "Avelinópolis", "serie": [{"ano": 1985, "lulc_area_total_ha": 17022.230115746203, "lulc_vegetacao_nativa_ha": 3956.0637181826355, "lulc_pastagem_ha": 10365.48024120938, "lulc_soja_ha": 0.0, "lulc_agricultura_ha": 0.0, "lulc_mosaico_usos_ha": 2649.369754053161, "lulc_corpo_dagua_ha": 27.71499118652342, "lulc_area_urbana_ha": 21.45592206420898, "pec_bovinos_cab": 17000.0, "pec_bovinos_ua": 11900.0, "pec_suinos_cab": 2700.0, "pec_galinaceos_cab": 10680.0, "pec_ovinos_tosquiados_cab": 15.0, "agri_soja_ton": null, "agri_milho_total_ton": 7150.0, "agri_cana_ton": 14400.0, "agri_algodao_ton": null, "agri_mandioca_ton": 380.0, "agri_arroz_ton": 810.0, "agri_sorgo_ton": null, "agri_feijao_ton": 624.0, "agri_leite_mil_litros": 1416.0, "perm_cafe_total_ton": 24.0, "perm_banana_ton": 8.0, "perm_laranja_ton": 320.0, "perm_manga_ton": null, "perm_mamao_ton": null, "perm_maracuja_ton": null, "perm_uva_ton": null, "pib_real_rs": null, "populacao": null, "sicor_total_real_rs": null, "fogo_total_ha": 37.8, "lotacao_bov_ha_pasto": null, "lotacao_ua_ha_pasto": 1.1480413567998449, "pct_pastagem_lulc": 60.8938, "pct_agricultura_lulc": 0.0, "pct_natural_lulc": 22.7788, "pct_vegetacao_nativa": 0.2324}, {"ano": 1986, "lulc_area_total_ha": 17022.230115746108, "lulc_vegetacao_nativa_ha": 3771.311100390943, "lulc_pastagem_ha": 11182.06217794035, "lulc_soja_ha": 0.0, "lulc_agricultura_ha": 0.0, "lulc_mosaico_usos_ha": 2017.197686822772, "lulc_corpo_dagua_ha": 28.22936436767577, "lulc_area_urbana_ha": 21.54174434204102, "pec_bovinos_cab": 17500.0, "pec_bovinos_ua": 12250.0, "pec_suinos_cab": 2800.0, "pec_galinaceos_cab": 10780.0, "pec_ovinos_tosquiados_cab": 14.0, "agri_soja_ton": null, "agri_milho_total_ton": 6690.0, "agri_cana_ton": 27000.0, "agri_algodao_ton": null, "agri_mandioca_ton": 608.0, "agri_arroz_ton": 945.0, "agri_sorgo_ton": null, "agri_feijao_ton": 293.0, "agri_leite_mil_litros": 1430.0, "perm_cafe_total_ton": 24.0, "perm_banana_ton": 4.0, "perm_laranja_ton": 320.0, "perm_manga_ton": null, "perm_mamao_ton": null, "perm_maracuja_ton": null, "perm_uva_ton": null, "pib_real_rs": null, "populacao": null, "sicor_total_real_rs": null, "fogo_total_ha": 2.88, "lotacao_bov_ha_pasto": null, "lotacao_ua_ha_pasto": 1.0955045505082637, "pct_pastagem_lulc": 65.6909, "pct_agricultura_lulc": 0.0, "pct_natural_lulc": 21.701, "pct_vegetacao_nativa": 0.2216}, {"ano": 1987, "lulc_area_total_ha": 17022.23011574586, "lulc_vegetacao_nativa_ha": 3638.3086209293374, "lulc_pastagem_ha": 11882.26582568809, "lulc_soja_ha": 0.0, "lulc_agricultura_ha": 9.267418243408208, "lulc_mosaico_usos_ha": 1441.672776458754, "lulc_corpo_dagua_ha": 27.11417434082031, "lulc_area_urbana_ha": 21.88503859252929, "pec_bovinos_cab": 18000.0, "pec_bovinos_ua": 12600.0, "pec_suinos_cab": 2850.0, "pec_galinaceos_cab": 10850.0, "pec_ovinos_tosquiados_cab": 15.0, "agri_soja_ton": null, "agri_milho_total_ton": 7130.0, "agri_cana_ton": 22500.0, "agri_algodao_ton": null, "agri_mandioca_ton": 600.0, "agri_arroz_ton": 780.0, "agri_sorgo_ton": null, "agri_feijao_ton": 540.0, "agri_leite_mil_litros": 1469.0, "perm_cafe_total_ton": 30.0, "perm_banana_ton": 15.0, "perm_laranja_ton": null, "perm_manga_ton": null, "perm_mamao_ton": null, "perm_maracuja_ton": null, "perm_uva_ton": null, "pib_real_rs": null, "populacao": null, "sicor_total_real_rs": null, "fogo_total_ha": 83.05, "lotacao_bov_ha_pasto": null, "lotacao_ua_ha_pasto": 1.0604038139561103, "pct_pastagem_lulc": 69.8044, "pct_agricultura_lulc": 0.0544, "pct_natural_lulc": 20.9202, "pct_vegetacao_nativa": 0.2137}, {"ano": 1988, "lulc_area_total_ha": 17022.230115746017, "lulc_vegetacao_nativa_ha": 3563.477242499174, "lulc_pastagem_ha": 12099.4562038926, "lulc_soja_ha": 2.574329315185547, "lulc_agricultura_ha": 175.12944944458062, "lulc_mosaico_usos_ha": 1128.301566503899, "lulc_corpo_dagua_ha": 27.02844782714843, "lulc_area_urbana_ha": 21.88503859252929, "pec_bovinos_cab": 17500.0, "pec_bovinos_ua": 12250.0, "pec_suinos_cab": 2500.0, "pec_galinaceos_cab": 9870.0, "pec_ovinos_tosquiados_cab": 20.0, "agri_soja_ton": null, "agri_milho_total_ton": 6760.0, "agri_cana_ton": 21000.0, "agri_algodao_ton": null, "agri_mandioca_ton": 600.0, "agri_arroz_ton": 800.0, "agri_sorgo_ton": null, "agri_feijao_ton": 400.0, "agri_leite_mil_litros": 1425.0, "perm_cafe_total_ton": 20.0, "perm_banana_ton": 15.0, "perm_laranja_ton": 210.0, "perm_manga_ton": null, "perm_mamao_ton": null, "perm_maracuja_ton": null, "perm_uva_ton": null, "pib_real_rs": null, "populacao": null, "sicor_total_real_rs": null, "fogo_total_ha": 274.41, "lotacao_bov_ha_pasto": null, "lotacao_ua_ha_pasto": 1.0124421952169196, "pct_pastagem_lulc": 71.0803, "pct_agricultura_lulc": 1.0288, "pct_natural_lulc": 20.5128, "pct_vegetacao_nativa": 0.2093}, {"ano": 1989, "lulc_area_total_ha": 17022.230115746246, "lulc_vegetacao_nativa_ha": 3512.2440523990817, "lulc_pastagem_ha": 12205.00956622192, "lulc_soja_ha": 11.75610800170899, "lulc_agricultura_ha": 187.1428075378424, "lulc_mosaico_usos_ha": 1056.647171307371, "lulc_corpo_dagua_ha": 26.0846250061035, "lulc_area_urbana_ha": 21.88503859252929, "pec_bovinos_cab": 17000.0, "pec_bovinos_ua": 11900.0, "pec_suinos_cab": 2600.0, "pec_galinaceos_cab": 9800.0, "pec_ovinos_tosquiados_cab": 15.0, "agri_soja_ton": null, "agri_milho_total_ton": 7770.0, "agri_cana_ton": null, "agri_algodao_ton": null, "agri_mandioca_ton": 450.0, "agri_arroz_ton": 920.0, "agri_sorgo_ton": null, "agri_feijao_ton": 600.0, "agri_leite_mil_litros": 1430.0, "perm_cafe_total_ton": 19.0, "perm_banana_ton": 10.0, "perm_laranja_ton": 220.0, "perm_manga_ton": null, "perm_mamao_ton": null, "perm_maracuja_ton": null, "perm_uva_ton": null, "pib_real_rs": null, "populacao": null, "sicor_total_real_rs": null, "fogo_total_ha": 7.74, "lotacao_bov_ha_pasto": null, "lotacao_ua_ha_pasto": 0.975009477496351, "pct_pastagem_lulc": 71.7004, "pct_agricultura_lulc": 1.0994, "pct_natural_lulc": 20.224, "pct_vegetacao_nativa": 0.2063}, {"ano": 1990, "lulc_area_total_ha": 17022.230115746097, "lulc_vegetacao_nativa_ha": 3404.369064844163, "lulc_pastagem_ha": 12198.41226556258, "lulc_soja_ha": 12.87198424072266, "lulc_agricultura_ha": 246.09175147705136, "lulc_mosaico_usos_ha": 1093.891106640621, "lulc_corpo_dagua_ha": 28.74458527832029, "lulc_area_urbana_ha": 22.14251195678711, "pec_bovinos_cab": 17420.0, "pec_bovinos_ua": 12194.0, "pec_suinos_cab": 2660.0, "pec_galinaceos_cab": 10000.0, "pec_ovinos_tosquiados_cab": 18.0, "agri_soja_ton": null, "agri_milho_total_ton": 5000.0, "agri_cana_ton": null, "agri_algodao_ton": null, "agri_mandioca_ton": 380.0, "agri_arroz_ton": 720.0, "agri_sorgo_ton": null, "agri_feijao_ton": 1300.0, "agri_leite_mil_litros": 1460.0, "perm_cafe_total_ton": 33.0, "perm_banana_ton": 5.0, "perm_laranja_ton": 240.0, "perm_manga_ton": null, "perm_mamao_ton": null, "perm_maracuja_ton": null, "perm_uva_ton": null, "pib_real_rs": null, "populacao": null, "sicor_total_real_rs": null, "fogo_total_ha": 0.0, "lotacao_bov_ha_pasto": null, "lotacao_ua_ha_pasto": 0.9996382918148261, "pct_pastagem_lulc": 71.6617, "pct_agricultura_lulc": 1.4457, "pct_natural_lulc": 19.6074, "pct_vegetacao_nativa": 0.2}, {"ano": 1991, "lulc_area_total_ha": 17022.23011574611, "lulc_vegetacao_nativa_ha": 3333.052953735777, "lulc_pastagem_ha": 12209.66233561263, "lulc_soja_ha": 42.90196354980465, "lulc_agricultura_ha": 278.86749820556656, "lulc_mosaico_usos_ha": 1082.650039422607, "lulc_corpo_dagua_ha": 29.51723787231444, "lulc_area_urbana_ha": 22.82910673217773, "pec_bovinos_cab": 18400.0, "pec_bovinos_ua": 12880.0, "pec_suinos_cab": 2320.0, "pec_galinaceos_cab": 10310.0, "pec_ovinos_tosquiados_cab": null, "agri_soja_ton": null, "agri_milho_total_ton": 4500.0, "agri_cana_ton": null, "agri_algodao_ton": null, "agri_mandioca_ton": 380.0, "agri_arroz_ton": 1000.0, "agri_sorgo_ton": null, "agri_feijao_ton": 1200.0, "agri_leite_mil_litros": 1478.0, "perm_cafe_total_ton": 40.0, "perm_banana_ton": 35.0, "perm_laranja_ton": 361.0, "perm_manga_ton": null, "perm_mamao_ton": null, "perm_maracuja_ton": null, "perm_uva_ton": null, "pib_real_rs": null, "populacao": null, "sicor_total_real_rs": null, "fogo_total_ha": 0.0, "lotacao_bov_ha_pasto": null, "lotacao_ua_ha_pasto": 1.0549022279209277, "pct_pastagem_lulc": 71.7277, "pct_agricultura_lulc": 1.6383, "pct_natural_lulc": 19.2524, "pct_vegetacao_nativa": 0.1958}, {"ano": 1992, "lulc_area_total_ha": 17022.23011574628, "lulc_vegetacao_nativa_ha": 3254.8739271549803, "lulc_pastagem_ha": 12313.83002218505, "lulc_soja_ha": 27.80317719116211, "lulc_agricultura_ha": 200.18747700195377, "lulc_mosaico_usos_ha": 1127.016129858395, "lulc_corpo_dagua_ha": 30.03213975830076, "lulc_area_urbana_ha": 23.77317579345702, "pec_bovinos_cab": 18750.0, "pec_bovinos_ua": 13125.0, "pec_suinos_cab": 2570.0, "pec_galinaceos_cab": 10550.0, "pec_ovinos_tosquiados_cab": null, "agri_soja_ton": null, "agri_milho_total_ton": 4800.0, "agri_cana_ton": null, "agri_algodao_ton": null, "agri_mandioca_ton": 450.0, "agri_arroz_ton": 900.0, "agri_sorgo_ton": null, "agri_feijao_ton": 1200.0, "agri_leite_mil_litros": 1560.0, "perm_cafe_total_ton": 50.0, "perm_banana_ton": 27.0, "perm_laranja_ton": 722.0, "perm_manga_ton": null, "perm_mamao_ton": null, "perm_maracuja_ton": null, "perm_uva_ton": null, "pib_real_rs": null, "populacao": null, "sicor_total_real_rs": null, "fogo_total_ha": 8.37, "lotacao_bov_ha_pasto": null, "lotacao_ua_ha_pasto": 1.0658747096844374, "pct_pastagem_lulc": 72.3397, "pct_agricultura_lulc": 1.176, "pct_natural_lulc": 18.8063, "pct_vegetacao_nativa": 0.1912}, {"ano": 1993, "lulc_area_total_ha": 17022.230115746406, "lulc_vegetacao_nativa_ha": 3098.1065684331106, "lulc_pastagem_ha": 12393.45041683844, "lulc_soja_ha": 29.09189722290039, "lulc_agricultura_ha": 226.3609333862306, "lulc_mosaico_usos_ha": 1176.359256719974, "lulc_corpo_dagua_ha": 30.03215192871092, "lulc_area_urbana_ha": 28.06432869262691, "pec_bovinos_cab": 19870.0, "pec_bovinos_ua": 13909.0, "pec_suinos_cab": 2680.0, "pec_galinaceos_cab": 10760.0, "pec_ovinos_tosquiados_cab": null, "agri_soja_ton": null, "agri_milho_total_ton": 5000.0, "agri_cana_ton": null, "agri_algodao_ton": null, "agri_mandioca_ton": 450.0, "agri_arroz_ton": 900.0, "agri_sorgo_ton": null, "agri_feijao_ton": 1000.0, "agri_leite_mil_litros": 1651.0, "perm_cafe_total_ton": 50.0, "perm_banana_ton": 27.0, "perm_laranja_ton": 722.0, "perm_manga_ton": null, "perm_mamao_ton": null, "perm_maracuja_ton": null, "perm_uva_ton": null, "pib_real_rs": null, "populacao": null, "sicor_total_real_rs": null, "fogo_total_ha": 58.44, "lotacao_bov_ha_pasto": null, "lotacao_ua_ha_pasto": 1.1222863312627167, "pct_pastagem_lulc": 72.8074, "pct_agricultura_lulc": 1.3298, "pct_natural_lulc": 17.8939, "pct_vegetacao_nativa": 0.182}, {"ano": 1994, "lulc_area_total_ha": 17022.23011574661, "lulc_vegetacao_nativa_ha": 3022.1655729741215, "lulc_pastagem_ha": 12547.37684878445, "lulc_soja_ha": 22.22529840087891, "lulc_agricultura_ha": 221.73109804077217, "lulc_mosaico_usos_ha": 1103.345514129639, "lulc_corpo_dagua_ha": 28.40200850219725, "lulc_area_urbana_ha": 36.47484464721686, "pec_bovinos_cab": 20660.0, "pec_bovinos_ua": 14461.999999999998, "pec_suinos_cab": 2800.0, "pec_galinaceos_cab": 11180.0, "pec_ovinos_tosquiados_cab": null, "agri_soja_ton": null, "agri_milho_total_ton": 5580.0, "agri_cana_ton": null, "agri_algodao_ton": null, "agri_mandioca_ton": 450.0, "agri_arroz_ton": 900.0, "agri_sorgo_ton": null, "agri_feijao_ton": 910.0, "agri_leite_mil_litros": 1802.0, "perm_cafe_total_ton": 16.0, "perm_banana_ton": 27.0, "perm_laranja_ton": 1056.0, "perm_manga_ton": null, "perm_mamao_ton": null, "perm_maracuja_ton": null, "perm_uva_ton": null, "pib_real_rs": null, "populacao": null, "sicor_total_real_rs": null, "fogo_total_ha": 21.86, "lotacao_bov_ha_pasto": null, "lotacao_ua_ha_pasto": 1.152591507714302, "pct_pastagem_lulc": 73.7117, "pct_agricultura_lulc": 1.3026, "pct_natural_lulc": 17.4609, "pct_vegetacao_nativa": 0.1775}, {"ano": 1995, "lulc_area_total_ha": 17022.230115746614, "lulc_vegetacao_nativa_ha": 2942.1872250187876, "lulc_pastagem_ha": 12631.12044744779, "lulc_soja_ha": 65.476502923584, "lulc_agricultura_ha": 277.17210666503985, "lulc_mosaico_usos_ha": 1038.045376995854, "lulc_corpo_dagua_ha": 28.74531615600585, "lulc_area_urbana_ha": 42.39661276245139, "pec_bovinos_cab": 21890.0, "pec_bovinos_ua": 15322.999999999998, "pec_suinos_cab": 2980.0, "pec_galinaceos_cab": 11730.0, "pec_ovinos_tosquiados_cab": null, "agri_soja_ton": null, "agri_milho_total_ton": 6000.0, "agri_cana_ton": null, "agri_algodao_ton": null, "agri_mandioca_ton": 450.0, "agri_arroz_ton": 1220.0, "agri_sorgo_ton": null, "agri_feijao_ton": 1116.0, "agri_leite_mil_litros": 1913.0, "perm_cafe_total_ton": 16.0, "perm_banana_ton": 27.0, "perm_laranja_ton": 1056.0, "perm_manga_ton": null, "perm_mamao_ton": null, "perm_maracuja_ton": null, "perm_uva_ton": null, "pib_real_rs": null, "populacao": null, "sicor_total_real_rs": null, "fogo_total_ha": 1.44, "lotacao_bov_ha_pasto": null, "lotacao_ua_ha_pasto": 1.2131148668680554, "pct_pastagem_lulc": 74.2037, "pct_agricultura_lulc": 1.6283, "pct_natural_lulc": 17.0041, "pct_vegetacao_nativa": 0.1728}, {"ano": 1996, "lulc_area_total_ha": 17022.230115746286, "lulc_vegetacao_nativa_ha": 2862.035581226023, "lulc_pastagem_ha": 12273.89641370727, "lulc_soja_ha": 107.868376715088, "lulc_agricultura_ha": 677.5699509948677, "lulc_mosaico_usos_ha": 1067.556239855967, "lulc_corpo_dagua_ha": 27.45839669799803, "lulc_area_urbana_ha": 48.23244244384786, "pec_bovinos_cab": 16544.0, "pec_bovinos_ua": 11580.8, "pec_suinos_cab": 2724.0, "pec_galinaceos_cab": 139486.0, "pec_ovinos_tosquiados_cab": null, "agri_soja_ton": null, "agri_milho_total_ton": 2650.0, "agri_cana_ton": null, "agri_algodao_ton": null, "agri_mandioca_ton": 305.0, "agri_arroz_ton": 1440.0, "agri_sorgo_ton": null, "agri_feijao_ton": 750.0, "agri_leite_mil_litros": 2626.0, "perm_cafe_total_ton": 2.0, "perm_banana_ton": 175.0, "perm_laranja_ton": 140.0, "perm_manga_ton": null, "perm_mamao_ton": null, "perm_maracuja_ton": null, "perm_uva_ton": null, "pib_real_rs": null, "populacao": null, "sicor_total_real_rs": null, "fogo_total_ha": 21.24, "lotacao_bov_ha_pasto": null, "lotacao_ua_ha_pasto": 0.9435308568407638, "pct_pastagem_lulc": 72.1051, "pct_agricultura_lulc": 3.9805, "pct_natural_lulc": 16.5322, "pct_vegetacao_nativa": 0.1681}, {"ano": 1997, "lulc_area_total_ha": 17022.230115746137, "lulc_vegetacao_nativa_ha": 2807.541534155716, "lulc_pastagem_ha": 12333.89089590926, "lulc_soja_ha": 49.59517639770492, "lulc_agricultura_ha": 692.4129221557553, "lulc_mosaico_usos_ha": 1046.697895397963, "lulc_corpo_dagua_ha": 27.54421488037108, "lulc_area_urbana_ha": 50.97871932373073, "pec_bovinos_cab": 21155.0, "pec_bovinos_ua": 14808.499999999998, "pec_suinos_cab": 2795.0, "pec_galinaceos_cab": 139805.0, "pec_ovinos_tosquiados_cab": null, "agri_soja_ton": null, "agri_milho_total_ton": 3900.0, "agri_cana_ton": null, "agri_algodao_ton": null, "agri_mandioca_ton": 305.0, "agri_arroz_ton": 1760.0, "agri_sorgo_ton": null, "agri_feijao_ton": 750.0, "agri_leite_mil_litros": 4623.0, "perm_cafe_total_ton": 2.0, "perm_banana_ton": 189.0, "perm_laranja_ton": 190.0, "perm_manga_ton": null, "perm_mamao_ton": null, "perm_maracuja_ton": null, "perm_uva_ton": null, "pib_real_rs": null, "populacao": null, "sicor_total_real_rs": null, "fogo_total_ha": 1.8, "lotacao_bov_ha_pasto": null, "lotacao_ua_ha_pasto": 1.2006349111545558, "pct_pastagem_lulc": 72.4575, "pct_agricultura_lulc": 4.0677, "pct_natural_lulc": 16.2121, "pct_vegetacao_nativa": 0.1649}, {"ano": 1998, "lulc_area_total_ha": 17022.23011574653, "lulc_vegetacao_nativa_ha": 2798.61598198286, "lulc_pastagem_ha": 12718.17295006615, "lulc_soja_ha": 17.33157731933595, "lulc_agricultura_ha": 368.29583063354477, "lulc_mosaico_usos_ha": 1018.544246380628, "lulc_corpo_dagua_ha": 27.45870337524412, "lulc_area_urbana_ha": 52.78097242431669, "pec_bovinos_cab": 21790.0, "pec_bovinos_ua": 15252.999999999998, "pec_suinos_cab": 2910.0, "pec_galinaceos_cab": 144090.0, "pec_ovinos_tosquiados_cab": null, "agri_soja_ton": null, "agri_milho_total_ton": 3250.0, "agri_cana_ton": 16000.0, "agri_algodao_ton": null, "agri_mandioca_ton": 300.0, "agri_arroz_ton": 660.0, "agri_sorgo_ton": null, "agri_feijao_ton": 211.0, "agri_leite_mil_litros": 4598.0, "perm_cafe_total_ton": null, "perm_banana_ton": 92.0, "perm_laranja_ton": 910.0, "perm_manga_ton": null, "perm_mamao_ton": null, "perm_maracuja_ton": null, "perm_uva_ton": null, "pib_real_rs": null, "populacao": null, "sicor_total_real_rs": null, "fogo_total_ha": 148.86, "lotacao_bov_ha_pasto": null, "lotacao_ua_ha_pasto": 1.1993074838568432, "pct_pastagem_lulc": 74.7151, "pct_agricultura_lulc": 2.1636, "pct_natural_lulc": 16.1541, "pct_vegetacao_nativa": 0.1644}, {"ano": 1999, "lulc_area_total_ha": 17022.230115746395, "lulc_vegetacao_nativa_ha": 2768.5802871220208, "lulc_pastagem_ha": 12748.05229630625, "lulc_soja_ha": 42.30274690551744, "lulc_agricultura_ha": 324.3590487121579, "lulc_mosaico_usos_ha": 1060.064352435313, "lulc_corpo_dagua_ha": 35.78298969726561, "lulc_area_urbana_ha": 54.23993068847681, "pec_bovinos_cab": 23000.0, "pec_bovinos_ua": 16099.999999999998, "pec_suinos_cab": 3000.0, "pec_galinaceos_cab": 151000.0, "pec_ovinos_tosquiados_cab": null, "agri_soja_ton": null, "agri_milho_total_ton": 3250.0, "agri_cana_ton": 58000.0, "agri_algodao_ton": null, "agri_mandioca_ton": 300.0, "agri_arroz_ton": 660.0, "agri_sorgo_ton": null, "agri_feijao_ton": 211.0, "agri_leite_mil_litros": 6624.0, "perm_cafe_total_ton": null, "perm_banana_ton": 95.0, "perm_laranja_ton": 684.0, "perm_manga_ton": null, "perm_mamao_ton": null, "perm_maracuja_ton": null, "perm_uva_ton": null, "pib_real_rs": null, "populacao": null, "sicor_total_real_rs": null, "fogo_total_ha": 26.73, "lotacao_bov_ha_pasto": null, "lotacao_ua_ha_pasto": 1.2629380258084582, "pct_pastagem_lulc": 74.8906, "pct_agricultura_lulc": 1.9055, "pct_natural_lulc": 15.9827, "pct_vegetacao_nativa": 0.1626}, {"ano": 2000, "lulc_area_total_ha": 17022.230115746464, "lulc_vegetacao_nativa_ha": 2743.779902924028, "lulc_pastagem_ha": 12746.85876058244, "lulc_soja_ha": 37.15475892333978, "lulc_agricultura_ha": 277.4207470825196, "lulc_mosaico_usos_ha": 1144.152910522467, "lulc_corpo_dagua_ha": 30.11987069091796, "lulc_area_urbana_ha": 54.75486378784201, "pec_bovinos_cab": 25493.0, "pec_bovinos_ua": 17845.1, "pec_suinos_cab": 3040.0, "pec_galinaceos_cab": 154040.0, "pec_ovinos_tosquiados_cab": null, "agri_soja_ton": null, "agri_milho_total_ton": 3250.0, "agri_cana_ton": 58000.0, "agri_algodao_ton": null, "agri_mandioca_ton": 300.0, "agri_arroz_ton": 700.0, "agri_sorgo_ton": null, "agri_feijao_ton": 140.0, "agri_leite_mil_litros": 6962.0, "perm_cafe_total_ton": null, "perm_banana_ton": 125.0, "perm_laranja_ton": 430.0, "perm_manga_ton": null, "perm_mamao_ton": null, "perm_maracuja_ton": null, "perm_uva_ton": null, "pib_real_rs": null, "populacao": null, "sicor_total_real_rs": null, "fogo_total_ha": 21.6, "lotacao_bov_ha_pasto": null, "lotacao_ua_ha_pasto": 1.3999605969733524, "pct_pastagem_lulc": 74.8836, "pct_agricultura_lulc": 1.6298, "pct_natural_lulc": 15.8279, "pct_vegetacao_nativa": 0.1612}, {"ano": 2001, "lulc_area_total_ha": 17022.230115746177, "lulc_vegetacao_nativa_ha": 2697.448208227929, "lulc_pastagem_ha": 12649.46673100456, "lulc_soja_ha": 7.551072961425779, "lulc_agricultura_ha": 322.2076725708011, "lulc_mosaico_usos_ha": 1244.376626788346, "lulc_corpo_dagua_ha": 28.3180317626953, "lulc_area_urbana_ha": 54.75486065673848, "pec_bovinos_cab": 26257.0, "pec_bovinos_ua": 18379.899999999998, "pec_suinos_cab": 3148.0, "pec_galinaceos_cab": 157000.0, "pec_ovinos_tosquiados_cab": null, "agri_soja_ton": null, "agri_milho_total_ton": 3200.0, "agri_cana_ton": 18500.0, "agri_algodao_ton": null, "agri_mandioca_ton": 300.0, "agri_arroz_ton": 800.0, "agri_sorgo_ton": null, "agri_feijao_ton": 220.0, "agri_leite_mil_litros": 7205.0, "perm_cafe_total_ton": 36.0, "perm_banana_ton": 2000.0, "perm_laranja_ton": 90.0, "perm_manga_ton": null, "perm_mamao_ton": null, "perm_maracuja_ton": null, "perm_uva_ton": null, "pib_real_rs": null, "populacao": 2524.0, "sicor_total_real_rs": null, "fogo_total_ha": 15.85, "lotacao_bov_ha_pasto": null, "lotacao_ua_ha_pasto": 1.453017774650517, "pct_pastagem_lulc": 74.3115, "pct_agricultura_lulc": 1.8929, "pct_natural_lulc": 15.5593, "pct_vegetacao_nativa": 0.1585}, {"ano": 2002, "lulc_area_total_ha": 17022.230115745413, "lulc_vegetacao_nativa_ha": 2646.4798666324014, "lulc_pastagem_ha": 12342.67304474899, "lulc_soja_ha": 5.921113177490236, "lulc_agricultura_ha": 703.3811774475146, "lulc_mosaico_usos_ha": 1216.24492240601, "lulc_corpo_dagua_ha": 30.37765138549804, "lulc_area_urbana_ha": 54.84068584594747, "pec_bovinos_cab": 26500.0, "pec_bovinos_ua": 18550.0, "pec_suinos_cab": 3300.0, "pec_galinaceos_cab": 167000.0, "pec_ovinos_tosquiados_cab": null, "agri_soja_ton": null, "agri_milho_total_ton": 3200.0, "agri_cana_ton": 18500.0, "agri_algodao_ton": null, "agri_mandioca_ton": 300.0, "agri_arroz_ton": 800.0, "agri_sorgo_ton": null, "agri_feijao_ton": 220.0, "agri_leite_mil_litros": 7358.0, "perm_cafe_total_ton": 20.0, "perm_banana_ton": 3100.0, "perm_laranja_ton": 90.0, "perm_manga_ton": null, "perm_mamao_ton": null, "perm_maracuja_ton": null, "perm_uva_ton": null, "pib_real_rs": 43318270.456971765, "populacao": 2543.0, "sicor_total_real_rs": null, "fogo_total_ha": 24.77, "lotacao_bov_ha_pasto": null, "lotacao_ua_ha_pasto": 1.5029159350447046, "pct_pastagem_lulc": 72.5091, "pct_agricultura_lulc": 4.1321, "pct_natural_lulc": 15.2644, "pct_vegetacao_nativa": 0.1555}, {"ano": 2003, "lulc_area_total_ha": 17022.230115745213, "lulc_vegetacao_nativa_ha": 2600.9120012576113, "lulc_pastagem_ha": 12227.61531335235, "lulc_soja_ha": 3.260944915771485, "lulc_agricultura_ha": 797.5839552734328, "lulc_mosaico_usos_ha": 1277.261542803958, "lulc_corpo_dagua_ha": 31.83601099243162, "lulc_area_urbana_ha": 60.16165260620107, "pec_bovinos_cab": 26630.0, "pec_bovinos_ua": 18641.0, "pec_suinos_cab": 3317.0, "pec_galinaceos_cab": 167670.0, "pec_ovinos_tosquiados_cab": null, "agri_soja_ton": null, "agri_milho_total_ton": 2700.0, "agri_cana_ton": 18500.0, "agri_algodao_ton": null, "agri_mandioca_ton": 300.0, "agri_arroz_ton": 650.0, "agri_sorgo_ton": null, "agri_feijao_ton": 220.0, "agri_leite_mil_litros": 7422.0, "perm_cafe_total_ton": 20.0, "perm_banana_ton": 3100.0, "perm_laranja_ton": 90.0, "perm_manga_ton": null, "perm_mamao_ton": null, "perm_maracuja_ton": null, "perm_uva_ton": null, "pib_real_rs": 46514965.881387845, "populacao": 2560.0, "sicor_total_real_rs": null, "fogo_total_ha": 41.93, "lotacao_bov_ha_pasto": null, "lotacao_ua_ha_pasto": 1.5245000371940343, "pct_pastagem_lulc": 71.8332, "pct_agricultura_lulc": 4.6855, "pct_natural_lulc": 15.0023, "pct_vegetacao_nativa": 0.1528}, {"ano": 2004, "lulc_area_total_ha": 17022.230115745268, "lulc_vegetacao_nativa_ha": 2558.6048518252046, "lulc_pastagem_ha": 12056.34257520548, "lulc_soja_ha": 15.61936826171875, "lulc_agricultura_ha": 1017.3419724914384, "lulc_mosaico_usos_ha": 1266.707908728027, "lulc_corpo_dagua_ha": 33.89462630004881, "lulc_area_urbana_ha": 61.96391867065415, "pec_bovinos_cab": 26850.0, "pec_bovinos_ua": 18795.0, "pec_suinos_cab": 3360.0, "pec_galinaceos_cab": 167950.0, "pec_ovinos_tosquiados_cab": null, "agri_soja_ton": null, "agri_milho_total_ton": 4500.0, "agri_cana_ton": 18500.0, "agri_algodao_ton": null, "agri_mandioca_ton": 300.0, "agri_arroz_ton": 1400.0, "agri_sorgo_ton": null, "agri_feijao_ton": 270.0, "agri_leite_mil_litros": 7522.0, "perm_cafe_total_ton": 34.0, "perm_banana_ton": 3100.0, "perm_laranja_ton": 90.0, "perm_manga_ton": null, "perm_mamao_ton": null, "perm_maracuja_ton": null, "perm_uva_ton": null, "pib_real_rs": 47361276.53305376, "populacao": 2595.0, "sicor_total_real_rs": null, "fogo_total_ha": 38.25, "lotacao_bov_ha_pasto": null, "lotacao_ua_ha_pasto": 1.5589304868171987, "pct_pastagem_lulc": 70.827, "pct_agricultura_lulc": 5.9765, "pct_natural_lulc": 14.7512, "pct_vegetacao_nativa": 0.1503}, {"ano": 2005, "lulc_area_total_ha": 17022.230115745057, "lulc_vegetacao_nativa_ha": 2543.3304313967233, "lulc_pastagem_ha": 11985.21040699239, "lulc_soja_ha": 4.719220861816408, "lulc_agricultura_ha": 1093.197016693102, "lulc_mosaico_usos_ha": 1278.718204394533, "lulc_corpo_dagua_ha": 35.35308714599608, "lulc_area_urbana_ha": 63.93782797241204, "pec_bovinos_cab": 26960.0, "pec_bovinos_ua": 18872.0, "pec_suinos_cab": 3390.0, "pec_galinaceos_cab": 170500.0, "pec_ovinos_tosquiados_cab": null, "agri_soja_ton": null, "agri_milho_total_ton": 4400.0, "agri_cana_ton": 18000.0, "agri_algodao_ton": null, "agri_mandioca_ton": 300.0, "agri_arroz_ton": 1160.0, "agri_sorgo_ton": null, "agri_feijao_ton": 372.0, "agri_leite_mil_litros": 7676.0, "perm_cafe_total_ton": 40.0, "perm_banana_ton": 3200.0, "perm_laranja_ton": 90.0, "perm_manga_ton": null, "perm_mamao_ton": null, "perm_maracuja_ton": null, "perm_uva_ton": null, "pib_real_rs": 43548566.6637044, "populacao": 2614.0, "sicor_total_real_rs": null, "fogo_total_ha": 2.97, "lotacao_bov_ha_pasto": null, "lotacao_ua_ha_pasto": 1.5746073167801653, "pct_pastagem_lulc": 70.4092, "pct_agricultura_lulc": 6.4222, "pct_natural_lulc": 14.67, "pct_vegetacao_nativa": 0.1494}, {"ano": 2006, "lulc_area_total_ha": 17022.23011574504, "lulc_vegetacao_nativa_ha": 2520.2439866762484, "lulc_pastagem_ha": 11931.93290357441, "lulc_soja_ha": 4.890697760009767, "lulc_agricultura_ha": 1111.8151131286504, "lulc_mosaico_usos_ha": 1329.426871679695, "lulc_corpo_dagua_ha": 37.75592866210936, "lulc_area_urbana_ha": 67.02747910766591, "pec_bovinos_cab": 29000.0, "pec_bovinos_ua": 20300.0, "pec_suinos_cab": 3440.0, "pec_galinaceos_cab": 172000.0, "pec_ovinos_tosquiados_cab": null, "agri_soja_ton": 120.0, "agri_milho_total_ton": 5200.0, "agri_cana_ton": 20454.0, "agri_algodao_ton": null, "agri_mandioca_ton": 300.0, "agri_arroz_ton": 1450.0, "agri_sorgo_ton": 58.0, "agri_feijao_ton": 252.0, "agri_leite_mil_litros": 8080.0, "perm_cafe_total_ton": 56.0, "perm_banana_ton": 3491.0, "perm_laranja_ton": 300.0, "perm_manga_ton": null, "perm_mamao_ton": null, "perm_maracuja_ton": null, "perm_uva_ton": null, "pib_real_rs": 46550144.042365275, "populacao": 2633.0, "sicor_total_real_rs": null, "fogo_total_ha": 21.85, "lotacao_bov_ha_pasto": null, "lotacao_ua_ha_pasto": 1.7013169755521165, "pct_pastagem_lulc": 70.0962, "pct_agricultura_lulc": 6.5315, "pct_natural_lulc": 14.5394, "pct_vegetacao_nativa": 0.1481}, {"ano": 2007, "lulc_area_total_ha": 17022.230115745224, "lulc_vegetacao_nativa_ha": 2516.467166577377, "lulc_pastagem_ha": 11601.22258984778, "lulc_soja_ha": 56.72214404907231, "lulc_agricultura_ha": 1418.0724413879288, "lulc_mosaico_usos_ha": 1353.623378430187, "lulc_corpo_dagua_ha": 40.58772775878905, "lulc_area_urbana_ha": 68.4006305969237, "pec_bovinos_cab": 28500.0, "pec_bovinos_ua": 19950.0, "pec_suinos_cab": 3500.0, "pec_galinaceos_cab": 175000.0, "pec_ovinos_tosquiados_cab": null, "agri_soja_ton": 90.0, "agri_milho_total_ton": 5000.0, "agri_cana_ton": 28636.0, "agri_algodao_ton": null, "agri_mandioca_ton": 300.0, "agri_arroz_ton": 1160.0, "agri_sorgo_ton": 116.0, "agri_feijao_ton": 247.0, "agri_leite_mil_litros": 7725.0, "perm_cafe_total_ton": 56.0, "perm_banana_ton": 3491.0, "perm_laranja_ton": 300.0, "perm_manga_ton": null, "perm_mamao_ton": null, "perm_maracuja_ton": null, "perm_uva_ton": null, "pib_real_rs": 51054443.20775669, "populacao": null, "sicor_total_real_rs": null, "fogo_total_ha": 184.41, "lotacao_bov_ha_pasto": null, "lotacao_ua_ha_pasto": 1.7196463429171878, "pct_pastagem_lulc": 68.1534, "pct_agricultura_lulc": 8.3307, "pct_natural_lulc": 14.5243, "pct_vegetacao_nativa": 0.1478}, {"ano": 2008, "lulc_area_total_ha": 17022.230115745355, "lulc_vegetacao_nativa_ha": 2520.842902905503, "lulc_pastagem_ha": 11442.04247866012, "lulc_soja_ha": 22.05828967285157, "lulc_agricultura_ha": 1546.5252089721969, "lulc_mosaico_usos_ha": 1376.455909185806, "lulc_corpo_dagua_ha": 40.58782365722656, "lulc_area_urbana_ha": 73.72148140869116, "pec_bovinos_cab": 27600.0, "pec_bovinos_ua": 19320.0, "pec_suinos_cab": 3570.0, "pec_galinaceos_cab": 177000.0, "pec_ovinos_tosquiados_cab": null, "agri_soja_ton": 30.0, "agri_milho_total_ton": 6000.0, "agri_cana_ton": 94991.0, "agri_algodao_ton": null, "agri_mandioca_ton": 300.0, "agri_arroz_ton": 1400.0, "agri_sorgo_ton": 180.0, "agri_feijao_ton": 165.0, "agri_leite_mil_litros": 14100.0, "perm_cafe_total_ton": 56.0, "perm_banana_ton": 3491.0, "perm_laranja_ton": 300.0, "perm_manga_ton": null, "perm_mamao_ton": null, "perm_maracuja_ton": null, "perm_uva_ton": null, "pib_real_rs": 62663596.35693831, "populacao": 2431.0, "sicor_total_real_rs": null, "fogo_total_ha": 6.12, "lotacao_bov_ha_pasto": null, "lotacao_ua_ha_pasto": 1.6885097250803425, "pct_pastagem_lulc": 67.2182, "pct_agricultura_lulc": 9.0853, "pct_natural_lulc": 14.5611, "pct_vegetacao_nativa": 0.1481}, {"ano": 2009, "lulc_area_total_ha": 17022.230115745184, "lulc_vegetacao_nativa_ha": 2503.07949934105, "lulc_pastagem_ha": 11401.11428691188, "lulc_soja_ha": 10.04183981323242, "lulc_agricultura_ha": 1531.3314055176106, "lulc_mosaico_usos_ha": 1448.024423706089, "lulc_corpo_dagua_ha": 41.10258654174805, "lulc_area_urbana_ha": 75.43788140869103, "pec_bovinos_cab": 27000.0, "pec_bovinos_ua": 18900.0, "pec_suinos_cab": 3650.0, "pec_galinaceos_cab": 178500.0, "pec_ovinos_tosquiados_cab": null, "agri_soja_ton": 600.0, "agri_milho_total_ton": 8000.0, "agri_cana_ton": 94991.0, "agri_algodao_ton": null, "agri_mandioca_ton": 300.0, "agri_arroz_ton": 1800.0, "agri_sorgo_ton": 180.0, "agri_feijao_ton": 155.0, "agri_leite_mil_litros": 13195.0, "perm_cafe_total_ton": 56.0, "perm_banana_ton": 3491.0, "perm_laranja_ton": 300.0, "perm_manga_ton": null, "perm_mamao_ton": null, "perm_maracuja_ton": null, "perm_uva_ton": null, "pib_real_rs": 65974657.210744426, "populacao": 2421.0, "sicor_total_real_rs": null, "fogo_total_ha": 21.33, "lotacao_bov_ha_pasto": null, "lotacao_ua_ha_pasto": 1.6577327026443902, "pct_pastagem_lulc": 66.9778, "pct_agricultura_lulc": 8.9961, "pct_natural_lulc": 14.4598, "pct_vegetacao_nativa": 0.147}, {"ano": 2010, "lulc_area_total_ha": 17022.23011574533, "lulc_vegetacao_nativa_ha": 2510.80224050926, "lulc_pastagem_ha": 11364.89963147992, "lulc_soja_ha": 26.08750652465821, "lulc_agricultura_ha": 1568.1424833557455, "lulc_mosaico_usos_ha": 1439.533462902843, "lulc_corpo_dagua_ha": 40.50208338623047, "lulc_area_urbana_ha": 77.24009962768508, "pec_bovinos_cab": 27200.0, "pec_bovinos_ua": 19040.0, "pec_suinos_cab": 3680.0, "pec_galinaceos_cab": 178500.0, "pec_ovinos_tosquiados_cab": null, "agri_soja_ton": 750.0, "agri_milho_total_ton": 3200.0, "agri_cana_ton": 65995.0, "agri_algodao_ton": null, "agri_mandioca_ton": 300.0, "agri_arroz_ton": 82.0, "agri_sorgo_ton": 180.0, "agri_feijao_ton": 155.0, "agri_leite_mil_litros": 13500.0, "perm_cafe_total_ton": 56.0, "perm_banana_ton": 3491.0, "perm_laranja_ton": 300.0, "perm_manga_ton": null, "perm_mamao_ton": null, "perm_maracuja_ton": null, "perm_uva_ton": null, "pib_real_rs": 75015473.50248659, "populacao": null, "sicor_total_real_rs": null, "fogo_total_ha": 74.97, "lotacao_bov_ha_pasto": null, "lotacao_ua_ha_pasto": 1.675333757216881, "pct_pastagem_lulc": 66.765, "pct_agricultura_lulc": 9.2123, "pct_natural_lulc": 14.5041, "pct_vegetacao_nativa": 0.1475}, {"ano": 2011, "lulc_area_total_ha": 17022.230115745246, "lulc_vegetacao_nativa_ha": 2513.6326410280594, "lulc_pastagem_ha": 11381.80140772499, "lulc_soja_ha": 35.18385690307615, "lulc_agricultura_ha": 1582.214893524186, "lulc_mosaico_usos_ha": 1399.121614837639, "lulc_corpo_dagua_ha": 39.21511899414062, "lulc_area_urbana_ha": 78.01248479614213, "pec_bovinos_cab": 28000.0, "pec_bovinos_ua": 19600.0, "pec_suinos_cab": 3720.0, "pec_galinaceos_cab": 182000.0, "pec_ovinos_tosquiados_cab": null, "agri_soja_ton": null, "agri_milho_total_ton": 3200.0, "agri_cana_ton": 111401.0, "agri_algodao_ton": null, "agri_mandioca_ton": 300.0, "agri_arroz_ton": 82.0, "agri_sorgo_ton": null, "agri_feijao_ton": 120.0, "agri_leite_mil_litros": 14000.0, "perm_cafe_total_ton": 56.0, "perm_banana_ton": 3491.0, "perm_laranja_ton": 300.0, "perm_manga_ton": null, "perm_mamao_ton": null, "perm_maracuja_ton": null, "perm_uva_ton": null, "pib_real_rs": 89107670.06020214, "populacao": 2446.0, "sicor_total_real_rs": null, "fogo_total_ha": 170.52, "lotacao_bov_ha_pasto": null, "lotacao_ua_ha_pasto": 1.7220472663226405, "pct_pastagem_lulc": 66.8643, "pct_agricultura_lulc": 9.295, "pct_natural_lulc": 14.5213, "pct_vegetacao_nativa": 0.1477}, {"ano": 2012, "lulc_area_total_ha": 17022.23011574519, "lulc_vegetacao_nativa_ha": 2503.24815165428, "lulc_pastagem_ha": 11298.98108892612, "lulc_soja_ha": 72.51562390747048, "lulc_agricultura_ha": 1579.2981524108925, "lulc_mosaico_usos_ha": 1468.131612951654, "lulc_corpo_dagua_ha": 38.01383197631835, "lulc_area_urbana_ha": 82.9043426940915, "pec_bovinos_cab": 29400.0, "pec_bovinos_ua": 20580.0, "pec_suinos_cab": 3905.0, "pec_galinaceos_cab": 191100.0, "pec_ovinos_tosquiados_cab": null, "agri_soja_ton": 750.0, "agri_milho_total_ton": 4000.0, "agri_cana_ton": 111401.0, "agri_algodao_ton": null, "agri_mandioca_ton": 300.0, "agri_arroz_ton": 82.0, "agri_sorgo_ton": null, "agri_feijao_ton": 70.0, "agri_leite_mil_litros": 14700.0, "perm_cafe_total_ton": 56.0, "perm_banana_ton": 3491.0, "perm_laranja_ton": 300.0, "perm_manga_ton": null, "perm_mamao_ton": null, "perm_maracuja_ton": null, "perm_uva_ton": null, "pib_real_rs": 85792525.71336544, "populacao": 2442.0, "sicor_total_real_rs": null, "fogo_total_ha": 12.69, "lotacao_bov_ha_pasto": null, "lotacao_ua_ha_pasto": 1.8214031723771977, "pct_pastagem_lulc": 66.3778, "pct_agricultura_lulc": 9.2779, "pct_natural_lulc": 14.4588, "pct_vegetacao_nativa": 0.1471}, {"ano": 2013, "lulc_area_total_ha": 17022.23011574526, "lulc_vegetacao_nativa_ha": 2498.183750201645, "lulc_pastagem_ha": 11183.217633433, "lulc_soja_ha": 49.00007641601557, "lulc_agricultura_ha": 1659.1875151306383, "lulc_mosaico_usos_ha": 1508.126400915525, "lulc_corpo_dagua_ha": 34.23779069213867, "lulc_area_urbana_ha": 84.02003048095675, "pec_bovinos_cab": 30100.0, "pec_bovinos_ua": 21070.0, "pec_suinos_cab": 3975.0, "pec_galinaceos_cab": 191400.0, "pec_ovinos_tosquiados_cab": null, "agri_soja_ton": 1110.0, "agri_milho_total_ton": 2500.0, "agri_cana_ton": 112000.0, "agri_algodao_ton": null, "agri_mandioca_ton": null, "agri_arroz_ton": 80.0, "agri_sorgo_ton": null, "agri_feijao_ton": null, "agri_leite_mil_litros": 15000.0, "perm_cafe_total_ton": 120.0, "perm_banana_ton": 900.0, "perm_laranja_ton": 300.0, "perm_manga_ton": null, "perm_mamao_ton": null, "perm_maracuja_ton": null, "perm_uva_ton": null, "pib_real_rs": 88087528.8459802, "populacao": 2504.0, "sicor_total_real_rs": 10096003.767693028, "fogo_total_ha": 77.93, "lotacao_bov_ha_pasto": null, "lotacao_ua_ha_pasto": 1.8840731434046123, "pct_pastagem_lulc": 65.6977, "pct_agricultura_lulc": 9.7472, "pct_natural_lulc": 14.4305, "pct_vegetacao_nativa": 0.1468}, {"ano": 2014, "lulc_area_total_ha": 17022.230115745308, "lulc_vegetacao_nativa_ha": 2498.869581707995, "lulc_pastagem_ha": 11015.46046946817, "lulc_soja_ha": 71.91264180297836, "lulc_agricultura_ha": 1819.390466955633, "lulc_mosaico_usos_ha": 1501.094179742417, "lulc_corpo_dagua_ha": 34.49516549072265, "lulc_area_urbana_ha": 84.7065933715818, "pec_bovinos_cab": 31213.0, "pec_bovinos_ua": 21849.1, "pec_suinos_cab": 4134.0, "pec_galinaceos_cab": 198099.0, "pec_ovinos_tosquiados_cab": null, "agri_soja_ton": 1100.0, "agri_milho_total_ton": 2500.0, "agri_cana_ton": 119568.0, "agri_algodao_ton": null, "agri_mandioca_ton": null, "agri_arroz_ton": 80.0, "agri_sorgo_ton": null, "agri_feijao_ton": null, "agri_leite_mil_litros": 15540.0, "perm_cafe_total_ton": 120.0, "perm_banana_ton": 900.0, "perm_laranja_ton": 300.0, "perm_manga_ton": null, "perm_mamao_ton": null, "perm_maracuja_ton": null, "perm_uva_ton": null, "pib_real_rs": 83690810.52666073, "populacao": 2501.0, "sicor_total_real_rs": 12425917.870556904, "fogo_total_ha": 24.93, "lotacao_bov_ha_pasto": null, "lotacao_ua_ha_pasto": 1.9834940228381466, "pct_pastagem_lulc": 64.7122, "pct_agricultura_lulc": 10.6883, "pct_natural_lulc": 14.432, "pct_vegetacao_nativa": 0.1468}, {"ano": 2015, "lulc_area_total_ha": 17022.230115745355, "lulc_vegetacao_nativa_ha": 2494.2352379274807, "lulc_pastagem_ha": 10714.77026800946, "lulc_soja_ha": 256.3211963989252, "lulc_agricultura_ha": 2163.6732077271417, "lulc_mosaico_usos_ha": 1450.036484393285, "lulc_corpo_dagua_ha": 36.29693529052733, "lulc_area_urbana_ha": 86.76627540283187, "pec_bovinos_cab": 31080.0, "pec_bovinos_ua": 21756.0, "pec_suinos_cab": 4200.0, "pec_galinaceos_cab": 202500.0, "pec_ovinos_tosquiados_cab": null, "agri_soja_ton": 1600.0, "agri_milho_total_ton": 2920.0, "agri_cana_ton": 114000.0, "agri_algodao_ton": null, "agri_mandioca_ton": null, "agri_arroz_ton": null, "agri_sorgo_ton": null, "agri_feijao_ton": null, "agri_leite_mil_litros": 14350.0, "perm_cafe_total_ton": 190.0, "perm_banana_ton": 1100.0, "perm_laranja_ton": 300.0, "perm_manga_ton": null, "perm_mamao_ton": null, "perm_maracuja_ton": null, "perm_uva_ton": null, "pib_real_rs": 75595854.2691857, "populacao": 2499.0, "sicor_total_real_rs": 10011250.115615753, "fogo_total_ha": 53.64, "lotacao_bov_ha_pasto": null, "lotacao_ua_ha_pasto": 2.0304681720480535, "pct_pastagem_lulc": 62.9457, "pct_agricultura_lulc": 12.7109, "pct_natural_lulc": 14.4038, "pct_vegetacao_nativa": 0.1465}, {"ano": 2016, "lulc_area_total_ha": 17022.23011574523, "lulc_vegetacao_nativa_ha": 2491.8317550661523, "lulc_pastagem_ha": 10624.14885178624, "lulc_soja_ha": 637.7549254394542, "lulc_agricultura_ha": 2261.501965515168, "lulc_mosaico_usos_ha": 1442.829517059312, "lulc_corpo_dagua_ha": 37.75591597900389, "lulc_area_urbana_ha": 87.71031699218733, "pec_bovinos_cab": 32380.0, "pec_bovinos_ua": 22666.0, "pec_suinos_cab": 4360.0, "pec_galinaceos_cab": 210600.0, "pec_ovinos_tosquiados_cab": null, "agri_soja_ton": 1800.0, "agri_milho_total_ton": 3150.0, "agri_cana_ton": 105200.0, "agri_algodao_ton": null, "agri_mandioca_ton": null, "agri_arroz_ton": null, "agri_sorgo_ton": null, "agri_feijao_ton": null, "agri_leite_mil_litros": 4500.0, "perm_cafe_total_ton": 321.0, "perm_banana_ton": 960.0, "perm_laranja_ton": 210.0, "perm_manga_ton": null, "perm_mamao_ton": null, "perm_maracuja_ton": null, "perm_uva_ton": null, "pib_real_rs": 68260008.1032891, "populacao": 2496.0, "sicor_total_real_rs": 7084200.524345984, "fogo_total_ha": 48.03, "lotacao_bov_ha_pasto": null, "lotacao_ua_ha_pasto": 2.133441494109823, "pct_pastagem_lulc": 62.4134, "pct_agricultura_lulc": 13.2856, "pct_natural_lulc": 14.3952, "pct_vegetacao_nativa": 0.1464}, {"ano": 2017, "lulc_area_total_ha": 17022.23011574549, "lulc_vegetacao_nativa_ha": 2468.489339136001, "lulc_pastagem_ha": 10466.76846898006, "lulc_soja_ha": 793.1788743774407, "lulc_agricultura_ha": 2455.530596167045, "lulc_mosaico_usos_ha": 1428.837871368389, "lulc_corpo_dagua_ha": 38.87125126953123, "lulc_area_urbana_ha": 88.91181414794912, "pec_bovinos_cab": 32400.0, "pec_bovinos_ua": 22680.0, "pec_suinos_cab": 4400.0, "pec_galinaceos_cab": 210800.0, "pec_ovinos_tosquiados_cab": null, "agri_soja_ton": 1480.0, "agri_milho_total_ton": 2800.0, "agri_cana_ton": 110460.0, "agri_algodao_ton": null, "agri_mandioca_ton": null, "agri_arroz_ton": null, "agri_sorgo_ton": null, "agri_feijao_ton": null, "agri_leite_mil_litros": 4550.0, "perm_cafe_total_ton": 210.0, "perm_banana_ton": 1006.0, "perm_laranja_ton": 216.0, "perm_manga_ton": null, "perm_mamao_ton": null, "perm_maracuja_ton": null, "perm_uva_ton": null, "pib_real_rs": 68096582.92398456, "populacao": 2494.0, "sicor_total_real_rs": 8614849.024424395, "fogo_total_ha": 0.0, "lotacao_bov_ha_pasto": null, "lotacao_ua_ha_pasto": 2.1668579053043735, "pct_pastagem_lulc": 61.4888, "pct_agricultura_lulc": 14.4254, "pct_natural_lulc": 14.2682, "pct_vegetacao_nativa": 0.145}, {"ano": 2018, "lulc_area_total_ha": 17022.230115745537, "lulc_vegetacao_nativa_ha": 2458.533904138446, "lulc_pastagem_ha": 10383.10607185486, "lulc_soja_ha": 972.278413012699, "lulc_agricultura_ha": 2566.3235566895064, "lulc_mosaico_usos_ha": 1407.285854156474, "lulc_corpo_dagua_ha": 42.99067417602537, "lulc_area_urbana_ha": 89.9416851318359, "pec_bovinos_cab": 32800.0, "pec_bovinos_ua": 22960.0, "pec_suinos_cab": 680.0, "pec_galinaceos_cab": 125500.0, "pec_ovinos_tosquiados_cab": null, "agri_soja_ton": 2400.0, "agri_milho_total_ton": 708.0, "agri_cana_ton": 66470.0, "agri_algodao_ton": null, "agri_mandioca_ton": null, "agri_arroz_ton": null, "agri_sorgo_ton": null, "agri_feijao_ton": null, "agri_leite_mil_litros": 4250.0, "perm_cafe_total_ton": 210.0, "perm_banana_ton": 1006.0, "perm_laranja_ton": 216.0, "perm_manga_ton": null, "perm_mamao_ton": null, "perm_maracuja_ton": null, "perm_uva_ton": null, "pib_real_rs": 64287798.129626706, "populacao": 2425.0, "sicor_total_real_rs": 10503895.885727817, "fogo_total_ha": 54.78, "lotacao_bov_ha_pasto": null, "lotacao_ua_ha_pasto": 2.2112843537481437, "pct_pastagem_lulc": 60.9973, "pct_agricultura_lulc": 15.0763, "pct_natural_lulc": 14.2102, "pct_vegetacao_nativa": 0.1444}, {"ano": 2019, "lulc_area_total_ha": 17022.230115745442, "lulc_vegetacao_nativa_ha": 2455.015007892107, "lulc_pastagem_ha": 10312.98133704646, "lulc_soja_ha": 901.5876432678195, "lulc_agricultura_ha": 2600.7562783813482, "lulc_mosaico_usos_ha": 1445.895952905263, "lulc_corpo_dagua_ha": 44.96431911621092, "lulc_area_urbana_ha": 90.54244854736324, "pec_bovinos_cab": 30550.0, "pec_bovinos_ua": 21385.0, "pec_suinos_cab": 710.0, "pec_galinaceos_cab": 129200.0, "pec_ovinos_tosquiados_cab": null, "agri_soja_ton": 2400.0, "agri_milho_total_ton": 708.0, "agri_cana_ton": 110460.0, "agri_algodao_ton": null, "agri_mandioca_ton": null, "agri_arroz_ton": null, "agri_sorgo_ton": 2500.0, "agri_feijao_ton": null, "agri_leite_mil_litros": 4282.0, "perm_cafe_total_ton": 210.0, "perm_banana_ton": 1010.0, "perm_laranja_ton": 293.0, "perm_manga_ton": null, "perm_mamao_ton": null, "perm_maracuja_ton": null, "perm_uva_ton": null, "pib_real_rs": 67329954.80954325, "populacao": 2417.0, "sicor_total_real_rs": 5565075.636294007, "fogo_total_ha": 88.83, "lotacao_bov_ha_pasto": null, "lotacao_ua_ha_pasto": 2.0736001841853873, "pct_pastagem_lulc": 60.5854, "pct_agricultura_lulc": 15.2786, "pct_natural_lulc": 14.1895, "pct_vegetacao_nativa": 0.1442}, {"ano": 2020, "lulc_area_total_ha": 17022.230115745322, "lulc_vegetacao_nativa_ha": 2456.9876168337573, "lulc_pastagem_ha": 10222.62020007737, "lulc_soja_ha": 920.9771062011688, "lulc_agricultura_ha": 2604.5333008971966, "lulc_mosaico_usos_ha": 1524.842941180406, "lulc_corpo_dagua_ha": 48.65443727416987, "lulc_area_urbana_ha": 93.9752419433594, "pec_bovinos_cab": 32000.0, "pec_bovinos_ua": 22400.0, "pec_suinos_cab": 740.0, "pec_galinaceos_cab": 132500.0, "pec_ovinos_tosquiados_cab": null, "agri_soja_ton": 2420.0, "agri_milho_total_ton": 5004.0, "agri_cana_ton": 109110.0, "agri_algodao_ton": null, "agri_mandioca_ton": null, "agri_arroz_ton": null, "agri_sorgo_ton": 1500.0, "agri_feijao_ton": null, "agri_leite_mil_litros": 4410.0, "perm_cafe_total_ton": 212.0, "perm_banana_ton": 1010.0, "perm_laranja_ton": 270.0, "perm_manga_ton": null, "perm_mamao_ton": null, "perm_maracuja_ton": null, "perm_uva_ton": null, "pib_real_rs": 74854968.00833152, "populacao": 2409.0, "sicor_total_real_rs": 8838975.92135441, "fogo_total_ha": 363.1, "lotacao_bov_ha_pasto": null, "lotacao_ua_ha_pasto": 2.1912190379361314, "pct_pastagem_lulc": 60.0545, "pct_agricultura_lulc": 15.3008, "pct_natural_lulc": 14.2021, "pct_vegetacao_nativa": 0.1443}, {"ano": 2021, "lulc_area_total_ha": 17022.23011574531, "lulc_vegetacao_nativa_ha": 2454.6689001223326, "lulc_pastagem_ha": 10162.12729130658, "lulc_soja_ha": 942.9472879272432, "lulc_agricultura_ha": 2522.847614788798, "lulc_mosaico_usos_ha": 1667.108458374037, "lulc_corpo_dagua_ha": 49.94203719482418, "lulc_area_urbana_ha": 96.54980964965816, "pec_bovinos_cab": 31800.0, "pec_bovinos_ua": 22260.0, "pec_suinos_cab": 860.0, "pec_galinaceos_cab": 110500.0, "pec_ovinos_tosquiados_cab": null, "agri_soja_ton": 2950.0, "agri_milho_total_ton": 5200.0, "agri_cana_ton": 98500.0, "agri_algodao_ton": null, "agri_mandioca_ton": null, "agri_arroz_ton": null, "agri_sorgo_ton": 900.0, "agri_feijao_ton": null, "agri_leite_mil_litros": 4306.0, "perm_cafe_total_ton": 220.0, "perm_banana_ton": 1023.0, "perm_laranja_ton": 278.0, "perm_manga_ton": null, "perm_mamao_ton": null, "perm_maracuja_ton": null, "perm_uva_ton": null, "pib_real_rs": 78971492.36947714, "populacao": 2401.0, "sicor_total_real_rs": 28153177.351071168, "fogo_total_ha": 75.51, "lotacao_bov_ha_pasto": null, "lotacao_ua_ha_pasto": 2.19048623992762, "pct_pastagem_lulc": 59.6992, "pct_agricultura_lulc": 14.8209, "pct_natural_lulc": 14.19, "pct_vegetacao_nativa": 0.1442}, {"ano": 2022, "lulc_area_total_ha": 17022.230115745748, "lulc_vegetacao_nativa_ha": 2451.578967938495, "lulc_pastagem_ha": 9688.023749937209, "lulc_soja_ha": 1039.741347393801, "lulc_agricultura_ha": 2453.266919879147, "lulc_mosaico_usos_ha": 2213.539159881765, "lulc_corpo_dagua_ha": 48.31167473144528, "lulc_area_urbana_ha": 98.0946052246093, "pec_bovinos_cab": 31610.0, "pec_bovinos_ua": 22127.0, "pec_suinos_cab": 915.0, "pec_galinaceos_cab": 113800.0, "pec_ovinos_tosquiados_cab": null, "agri_soja_ton": 3400.0, "agri_milho_total_ton": 6550.0, "agri_cana_ton": 107800.0, "agri_algodao_ton": null, "agri_mandioca_ton": null, "agri_arroz_ton": null, "agri_sorgo_ton": 900.0, "agri_feijao_ton": null, "agri_leite_mil_litros": 4312.0, "perm_cafe_total_ton": 211.0, "perm_banana_ton": 1022.0, "perm_laranja_ton": 266.0, "perm_manga_ton": null, "perm_mamao_ton": null, "perm_maracuja_ton": null, "perm_uva_ton": null, "pib_real_rs": 94979129.7049819, "populacao": null, "sicor_total_real_rs": 24938431.925920986, "fogo_total_ha": 46.98, "lotacao_bov_ha_pasto": null, "lotacao_ua_ha_pasto": 2.283953938505096, "pct_pastagem_lulc": 56.914, "pct_agricultura_lulc": 14.4121, "pct_natural_lulc": 14.1774, "pct_vegetacao_nativa": 0.144}, {"ano": 2023, "lulc_area_total_ha": 17022.230115746203, "lulc_vegetacao_nativa_ha": 2447.1169387026557, "lulc_pastagem_ha": 9362.285408958294, "lulc_soja_ha": 1047.29384331055, "lulc_agricultura_ha": 2312.2227659179557, "lulc_mosaico_usos_ha": 2674.399773206117, "lulc_corpo_dagua_ha": 55.94949528198239, "lulc_area_urbana_ha": 99.03863587036128, "pec_bovinos_cab": 31625.0, "pec_bovinos_ua": 22137.5, "pec_suinos_cab": 1095.0, "pec_galinaceos_cab": 42000.0, "pec_ovinos_tosquiados_cab": null, "agri_soja_ton": 4071.0, "agri_milho_total_ton": 6442.0, "agri_cana_ton": 104320.0, "agri_algodao_ton": null, "agri_mandioca_ton": null, "agri_arroz_ton": null, "agri_sorgo_ton": 900.0, "agri_feijao_ton": null, "agri_leite_mil_litros": 6549.0, "perm_cafe_total_ton": 219.0, "perm_banana_ton": 480.0, "perm_laranja_ton": 271.0, "perm_manga_ton": null, "perm_mamao_ton": null, "perm_maracuja_ton": null, "perm_uva_ton": null, "pib_real_rs": 87647349.78565799, "populacao": null, "sicor_total_real_rs": 28182663.552587785, "fogo_total_ha": 3.24, "lotacao_bov_ha_pasto": null, "lotacao_ua_ha_pasto": 2.364540177211192, "pct_pastagem_lulc": 55.0003, "pct_agricultura_lulc": 13.5835, "pct_natural_lulc": 14.1517, "pct_vegetacao_nativa": 0.1438}, {"ano": 2024, "lulc_area_total_ha": 17022.230115746173, "lulc_vegetacao_nativa_ha": 2416.48229331691, "lulc_pastagem_ha": 9020.258282621731, "lulc_soja_ha": 1118.345875372319, "lulc_agricultura_ha": 2305.5320731445163, "lulc_mosaico_usos_ha": 3058.04300024456, "lulc_corpo_dagua_ha": 50.20015536499022, "lulc_area_urbana_ha": 99.6393794799804, "pec_bovinos_cab": 28545.0, "pec_bovinos_ua": 19981.5, "pec_suinos_cab": 1090.0, "pec_galinaceos_cab": 15385.0, "pec_ovinos_tosquiados_cab": null, "agri_soja_ton": 5510.0, "agri_milho_total_ton": 2450.0, "agri_cana_ton": 148200.0, "agri_algodao_ton": null, "agri_mandioca_ton": null, "agri_arroz_ton": null, "agri_sorgo_ton": 300.0, "agri_feijao_ton": null, "agri_leite_mil_litros": 5975.0, "perm_cafe_total_ton": null, "perm_banana_ton": 240.0, "perm_laranja_ton": null, "perm_manga_ton": null, "perm_mamao_ton": null, "perm_maracuja_ton": null, "perm_uva_ton": null, "pib_real_rs": null, "populacao": 2963.0, "sicor_total_real_rs": 18840072.36, "fogo_total_ha": 0.0, "lotacao_bov_ha_pasto": null, "lotacao_ua_ha_pasto": 2.2151804719933574, "pct_pastagem_lulc": 52.991, "pct_agricultura_lulc": 13.5442, "pct_natural_lulc": 13.9753, "pct_vegetacao_nativa": 0.142}]}