{"cd_mun": 5213756, "nm_mun": "Montividiu", "serie": [{"ano": 1985, "lulc_area_total_ha": 186962.6006590944, "lulc_vegetacao_nativa_ha": 47397.58440139788, "lulc_pastagem_ha": 53556.91868689543, "lulc_soja_ha": 26128.41300173449, "lulc_agricultura_ha": 62799.61149140004, "lulc_mosaico_usos_ha": 22716.66979424482, "lulc_corpo_dagua_ha": 160.3116159545899, "lulc_area_urbana_ha": 64.80903708496096, "pec_bovinos_cab": null, "pec_bovinos_ua": null, "pec_suinos_cab": null, "pec_galinaceos_cab": null, "pec_ovinos_tosquiados_cab": null, "agri_soja_ton": null, "agri_milho_total_ton": null, "agri_cana_ton": null, "agri_algodao_ton": null, "agri_mandioca_ton": null, "agri_arroz_ton": null, "agri_sorgo_ton": null, "agri_feijao_ton": null, "agri_leite_mil_litros": null, "perm_cafe_total_ton": null, "perm_banana_ton": null, "perm_laranja_ton": null, "perm_manga_ton": null, "perm_mamao_ton": null, "perm_maracuja_ton": null, "perm_uva_ton": null, "pib_real_rs": null, "populacao": null, "sicor_total_real_rs": null, "fogo_total_ha": 11539.58, "lotacao_bov_ha_pasto": null, "lotacao_ua_ha_pasto": null, "pct_pastagem_lulc": 28.6458, "pct_agricultura_lulc": 33.5894, "pct_natural_lulc": 18.7829, "pct_vegetacao_nativa": 0.2535}, {"ano": 1986, "lulc_area_total_ha": 186962.60065909257, "lulc_vegetacao_nativa_ha": 45146.39864606319, "lulc_pastagem_ha": 54992.56494891949, "lulc_soja_ha": 58740.87685154832, "lulc_agricultura_ha": 62904.03552153128, "lulc_mosaico_usos_ha": 23382.84422506152, "lulc_corpo_dagua_ha": 180.7360630065917, "lulc_area_urbana_ha": 68.05381248779302, "pec_bovinos_cab": null, "pec_bovinos_ua": null, "pec_suinos_cab": null, "pec_galinaceos_cab": null, "pec_ovinos_tosquiados_cab": null, "agri_soja_ton": null, "agri_milho_total_ton": null, "agri_cana_ton": null, "agri_algodao_ton": null, "agri_mandioca_ton": null, "agri_arroz_ton": null, "agri_sorgo_ton": null, "agri_feijao_ton": null, "agri_leite_mil_litros": null, "perm_cafe_total_ton": null, "perm_banana_ton": null, "perm_laranja_ton": null, "perm_manga_ton": null, "perm_mamao_ton": null, "perm_maracuja_ton": null, "perm_uva_ton": null, "pib_real_rs": null, "populacao": null, "sicor_total_real_rs": null, "fogo_total_ha": 4072.32, "lotacao_bov_ha_pasto": null, "lotacao_ua_ha_pasto": null, "pct_pastagem_lulc": 29.4137, "pct_agricultura_lulc": 33.6453, "pct_natural_lulc": 17.5851, "pct_vegetacao_nativa": 0.2415}, {"ano": 1987, "lulc_area_total_ha": 186962.6006591013, "lulc_vegetacao_nativa_ha": 43977.477673815985, "lulc_pastagem_ha": 52060.67827169993, "lulc_soja_ha": 68781.51557691552, "lulc_agricultura_ha": 71842.74281957299, "lulc_mosaico_usos_ha": 18534.6289384704, "lulc_corpo_dagua_ha": 187.9943401611327, "lulc_area_urbana_ha": 75.48319448242195, "pec_bovinos_cab": null, "pec_bovinos_ua": null, "pec_suinos_cab": null, "pec_galinaceos_cab": null, "pec_ovinos_tosquiados_cab": null, "agri_soja_ton": null, "agri_milho_total_ton": null, "agri_cana_ton": null, "agri_algodao_ton": null, "agri_mandioca_ton": null, "agri_arroz_ton": null, "agri_sorgo_ton": null, "agri_feijao_ton": null, "agri_leite_mil_litros": null, "perm_cafe_total_ton": null, "perm_banana_ton": null, "perm_laranja_ton": null, "perm_manga_ton": null, "perm_mamao_ton": null, "perm_maracuja_ton": null, "perm_uva_ton": null, "pib_real_rs": null, "populacao": null, "sicor_total_real_rs": null, "fogo_total_ha": 6950.52, "lotacao_bov_ha_pasto": null, "lotacao_ua_ha_pasto": null, "pct_pastagem_lulc": 27.8455, "pct_agricultura_lulc": 38.4263, "pct_natural_lulc": 16.9629, "pct_vegetacao_nativa": 0.2352}, {"ano": 1988, "lulc_area_total_ha": 186962.60065910273, "lulc_vegetacao_nativa_ha": 41458.20692412718, "lulc_pastagem_ha": 50872.67908605888, "lulc_soja_ha": 73481.18713984083, "lulc_agricultura_ha": 74855.89775878002, "lulc_mosaico_usos_ha": 19197.15982624503, "lulc_corpo_dagua_ha": 186.2009454406738, "lulc_area_urbana_ha": 107.7586916870118, "pec_bovinos_cab": null, "pec_bovinos_ua": null, "pec_suinos_cab": null, "pec_galinaceos_cab": null, "pec_ovinos_tosquiados_cab": null, "agri_soja_ton": null, "agri_milho_total_ton": null, "agri_cana_ton": null, "agri_algodao_ton": null, "agri_mandioca_ton": null, "agri_arroz_ton": null, "agri_sorgo_ton": null, "agri_feijao_ton": null, "agri_leite_mil_litros": null, "perm_cafe_total_ton": null, "perm_banana_ton": null, "perm_laranja_ton": null, "perm_manga_ton": null, "perm_mamao_ton": null, "perm_maracuja_ton": null, "perm_uva_ton": null, "pib_real_rs": null, "populacao": null, "sicor_total_real_rs": null, "fogo_total_ha": 8432.29, "lotacao_bov_ha_pasto": null, "lotacao_ua_ha_pasto": null, "pct_pastagem_lulc": 27.2101, "pct_agricultura_lulc": 40.0379, "pct_natural_lulc": 15.8565, "pct_vegetacao_nativa": 0.2217}, {"ano": 1989, "lulc_area_total_ha": 186962.60065910232, "lulc_vegetacao_nativa_ha": 39557.1196425966, "lulc_pastagem_ha": 46697.94264426041, "lulc_soja_ha": 81170.88837532114, "lulc_agricultura_ha": 85071.20165498422, "lulc_mosaico_usos_ha": 15076.14701726107, "lulc_corpo_dagua_ha": 199.0207312316894, "lulc_area_urbana_ha": 127.3123932495118, "pec_bovinos_cab": 50000.0, "pec_bovinos_ua": 35000.0, "pec_suinos_cab": 5000.0, "pec_galinaceos_cab": 46000.0, "pec_ovinos_tosquiados_cab": null, "agri_soja_ton": 73500.0, "agri_milho_total_ton": 93000.0, "agri_cana_ton": null, "agri_algodao_ton": 495.0, "agri_mandioca_ton": 980.0, "agri_arroz_ton": 1020.0, "agri_sorgo_ton": null, "agri_feijao_ton": 30.0, "agri_leite_mil_litros": 3400.0, "perm_cafe_total_ton": 50.0, "perm_banana_ton": null, "perm_laranja_ton": null, "perm_manga_ton": null, "perm_mamao_ton": null, "perm_maracuja_ton": null, "perm_uva_ton": null, "pib_real_rs": null, "populacao": null, "sicor_total_real_rs": null, "fogo_total_ha": 2177.52, "lotacao_bov_ha_pasto": null, "lotacao_ua_ha_pasto": 0.7494976870100253, "pct_pastagem_lulc": 24.9772, "pct_agricultura_lulc": 45.5017, "pct_natural_lulc": 15.0459, "pct_vegetacao_nativa": 0.2116}, {"ano": 1990, "lulc_area_total_ha": 186962.6006591006, "lulc_vegetacao_nativa_ha": 38218.65663547377, "lulc_pastagem_ha": 45257.720183206, "lulc_soja_ha": 82116.34113609942, "lulc_agricultura_ha": 90436.93148036217, "lulc_mosaico_usos_ha": 12542.43199693612, "lulc_corpo_dagua_ha": 182.6995871643066, "lulc_area_urbana_ha": 147.5494595947266, "pec_bovinos_cab": 50000.0, "pec_bovinos_ua": 35000.0, "pec_suinos_cab": 5200.0, "pec_galinaceos_cab": 47000.0, "pec_ovinos_tosquiados_cab": null, "agri_soja_ton": 41250.0, "agri_milho_total_ton": 49200.0, "agri_cana_ton": null, "agri_algodao_ton": 420.0, "agri_mandioca_ton": 980.0, "agri_arroz_ton": 650.0, "agri_sorgo_ton": null, "agri_feijao_ton": 1620.0, "agri_leite_mil_litros": 3400.0, "perm_cafe_total_ton": 90.0, "perm_banana_ton": null, "perm_laranja_ton": null, "perm_manga_ton": null, "perm_mamao_ton": null, "perm_maracuja_ton": null, "perm_uva_ton": null, "pib_real_rs": null, "populacao": null, "sicor_total_real_rs": null, "fogo_total_ha": 4356.0, "lotacao_bov_ha_pasto": null, "lotacao_ua_ha_pasto": 0.7733487205788951, "pct_pastagem_lulc": 24.2068, "pct_agricultura_lulc": 48.3717, "pct_natural_lulc": 14.603, "pct_vegetacao_nativa": 0.2044}, {"ano": 1991, "lulc_area_total_ha": 186962.60065910037, "lulc_vegetacao_nativa_ha": 35908.18203792111, "lulc_pastagem_ha": 44171.07416907067, "lulc_soja_ha": 85238.35375786423, "lulc_agricultura_ha": 95104.92415433642, "lulc_mosaico_usos_ha": 11289.16547171016, "lulc_corpo_dagua_ha": 187.4010444824219, "lulc_area_urbana_ha": 163.0913013427733, "pec_bovinos_cab": 53000.0, "pec_bovinos_ua": 37100.0, "pec_suinos_cab": 5290.0, "pec_galinaceos_cab": 45000.0, "pec_ovinos_tosquiados_cab": null, "agri_soja_ton": 54525.0, "agri_milho_total_ton": 128400.0, "agri_cana_ton": null, "agri_algodao_ton": 6250.0, "agri_mandioca_ton": 1050.0, "agri_arroz_ton": 9000.0, "agri_sorgo_ton": 929.0, "agri_feijao_ton": 1974.0, "agri_leite_mil_litros": 3655.0, "perm_cafe_total_ton": 40.0, "perm_banana_ton": null, "perm_laranja_ton": null, "perm_manga_ton": null, "perm_mamao_ton": null, "perm_maracuja_ton": null, "perm_uva_ton": null, "pib_real_rs": null, "populacao": null, "sicor_total_real_rs": null, "fogo_total_ha": 941.31, "lotacao_bov_ha_pasto": null, "lotacao_ua_ha_pasto": 0.8399161826582439, "pct_pastagem_lulc": 23.6256, "pct_agricultura_lulc": 50.8684, "pct_natural_lulc": 13.6205, "pct_vegetacao_nativa": 0.1921}, {"ano": 1992, "lulc_area_total_ha": 186962.60065910354, "lulc_vegetacao_nativa_ha": 34671.17434299927, "lulc_pastagem_ha": 43370.63603093805, "lulc_soja_ha": 81092.76022634079, "lulc_agricultura_ha": 95720.42351141125, "lulc_mosaico_usos_ha": 12718.80601359873, "lulc_corpo_dagua_ha": 195.5214809020997, "lulc_area_urbana_ha": 169.3246019775389, "pec_bovinos_cab": 60000.0, "pec_bovinos_ua": 42000.0, "pec_suinos_cab": 5290.0, "pec_galinaceos_cab": 41000.0, "pec_ovinos_tosquiados_cab": null, "agri_soja_ton": 72000.0, "agri_milho_total_ton": 135000.0, "agri_cana_ton": null, "agri_algodao_ton": 2800.0, "agri_mandioca_ton": 980.0, "agri_arroz_ton": 10600.0, "agri_sorgo_ton": 350.0, "agri_feijao_ton": 1810.0, "agri_leite_mil_litros": 4120.0, "perm_cafe_total_ton": null, "perm_banana_ton": null, "perm_laranja_ton": null, "perm_manga_ton": null, "perm_mamao_ton": null, "perm_maracuja_ton": null, "perm_uva_ton": null, "pib_real_rs": null, "populacao": null, "sicor_total_real_rs": null, "fogo_total_ha": 845.34, "lotacao_bov_ha_pasto": null, "lotacao_ua_ha_pasto": 0.9683971424822934, "pct_pastagem_lulc": 23.1975, "pct_agricultura_lulc": 51.1976, "pct_natural_lulc": 13.0833, "pct_vegetacao_nativa": 0.1854}, {"ano": 1993, "lulc_area_total_ha": 186962.60065910596, "lulc_vegetacao_nativa_ha": 33811.54544140627, "lulc_pastagem_ha": 42965.49985623686, "lulc_soja_ha": 80521.56644501365, "lulc_agricultura_ha": 98364.08299086336, "lulc_mosaico_usos_ha": 11280.35234562997, "lulc_corpo_dagua_ha": 191.9354234924317, "lulc_area_urbana_ha": 176.241069378662, "pec_bovinos_cab": 75000.0, "pec_bovinos_ua": 52500.0, "pec_suinos_cab": 5420.0, "pec_galinaceos_cab": 44000.0, "pec_ovinos_tosquiados_cab": null, "agri_soja_ton": 94860.0, "agri_milho_total_ton": 139550.0, "agri_cana_ton": null, "agri_algodao_ton": 1320.0, "agri_mandioca_ton": 1450.0, "agri_arroz_ton": 1660.0, "agri_sorgo_ton": 960.0, "agri_feijao_ton": 2210.0, "agri_leite_mil_litros": 6480.0, "perm_cafe_total_ton": null, "perm_banana_ton": null, "perm_laranja_ton": null, "perm_manga_ton": null, "perm_mamao_ton": null, "perm_maracuja_ton": null, "perm_uva_ton": null, "pib_real_rs": null, "populacao": null, "sicor_total_real_rs": null, "fogo_total_ha": 3922.64, "lotacao_bov_ha_pasto": null, "lotacao_ua_ha_pasto": 1.2219106067813876, "pct_pastagem_lulc": 22.9808, "pct_agricultura_lulc": 52.6116, "pct_natural_lulc": 12.8077, "pct_vegetacao_nativa": 0.1808}, {"ano": 1994, "lulc_area_total_ha": 186962.60065910954, "lulc_vegetacao_nativa_ha": 32959.83980999769, "lulc_pastagem_ha": 43119.09655120895, "lulc_soja_ha": 79690.8993715175, "lulc_agricultura_ha": 100581.72800063733, "lulc_mosaico_usos_ha": 9747.82750853267, "lulc_corpo_dagua_ha": 189.1190378173829, "lulc_area_urbana_ha": 181.7057125671384, "pec_bovinos_cab": 75000.0, "pec_bovinos_ua": 52500.0, "pec_suinos_cab": 5400.0, "pec_galinaceos_cab": 44000.0, "pec_ovinos_tosquiados_cab": null, "agri_soja_ton": 118800.0, "agri_milho_total_ton": 165500.0, "agri_cana_ton": null, "agri_algodao_ton": 302.0, "agri_mandioca_ton": 1450.0, "agri_arroz_ton": 3000.0, "agri_sorgo_ton": 3400.0, "agri_feijao_ton": 1200.0, "agri_leite_mil_litros": 6480.0, "perm_cafe_total_ton": null, "perm_banana_ton": null, "perm_laranja_ton": null, "perm_manga_ton": null, "perm_mamao_ton": null, "perm_maracuja_ton": null, "perm_uva_ton": null, "pib_real_rs": null, "populacao": null, "sicor_total_real_rs": null, "fogo_total_ha": 1850.46, "lotacao_bov_ha_pasto": null, "lotacao_ua_ha_pasto": 1.2175579777663044, "pct_pastagem_lulc": 23.063, "pct_agricultura_lulc": 53.7978, "pct_natural_lulc": 12.462, "pct_vegetacao_nativa": 0.1763}, {"ano": 1995, "lulc_area_total_ha": 186962.6006591069, "lulc_vegetacao_nativa_ha": 32221.56200225237, "lulc_pastagem_ha": 41073.28229176594, "lulc_soja_ha": 88065.11866261072, "lulc_agricultura_ha": 105287.45357226027, "lulc_mosaico_usos_ha": 7823.551326959151, "lulc_corpo_dagua_ha": 162.5445092468262, "lulc_area_urbana_ha": 193.2327769775387, "pec_bovinos_cab": 70000.0, "pec_bovinos_ua": 49000.0, "pec_suinos_cab": 5400.0, "pec_galinaceos_cab": 39000.0, "pec_ovinos_tosquiados_cab": null, "agri_soja_ton": 115500.0, "agri_milho_total_ton": 207200.0, "agri_cana_ton": null, "agri_algodao_ton": 1760.0, "agri_mandioca_ton": 1400.0, "agri_arroz_ton": 8800.0, "agri_sorgo_ton": 3800.0, "agri_feijao_ton": 920.0, "agri_leite_mil_litros": 5940.0, "perm_cafe_total_ton": null, "perm_banana_ton": null, "perm_laranja_ton": null, "perm_manga_ton": null, "perm_mamao_ton": null, "perm_maracuja_ton": null, "perm_uva_ton": null, "pib_real_rs": null, "populacao": null, "sicor_total_real_rs": null, "fogo_total_ha": 3251.48, "lotacao_bov_ha_pasto": null, "lotacao_ua_ha_pasto": 1.1929896337946955, "pct_pastagem_lulc": 21.9687, "pct_agricultura_lulc": 56.3147, "pct_natural_lulc": 12.1651, "pct_vegetacao_nativa": 0.1723}, {"ano": 1996, "lulc_area_total_ha": 186962.600659107, "lulc_vegetacao_nativa_ha": 31887.07480242936, "lulc_pastagem_ha": 39746.74347941276, "lulc_soja_ha": 85927.95703864179, "lulc_agricultura_ha": 107032.71599011897, "lulc_mosaico_usos_ha": 7675.331294061192, "lulc_corpo_dagua_ha": 172.1115158386231, "lulc_area_urbana_ha": 211.5915927185057, "pec_bovinos_cab": 67000.0, "pec_bovinos_ua": 46900.0, "pec_suinos_cab": 5400.0, "pec_galinaceos_cab": 18000.0, "pec_ovinos_tosquiados_cab": null, "agri_soja_ton": 112500.0, "agri_milho_total_ton": 153000.0, "agri_cana_ton": null, "agri_algodao_ton": 4200.0, "agri_mandioca_ton": 1400.0, "agri_arroz_ton": 12600.0, "agri_sorgo_ton": 14400.0, "agri_feijao_ton": 3780.0, "agri_leite_mil_litros": 6465.0, "perm_cafe_total_ton": null, "perm_banana_ton": null, "perm_laranja_ton": null, "perm_manga_ton": null, "perm_mamao_ton": null, "perm_maracuja_ton": null, "perm_uva_ton": null, "pib_real_rs": null, "populacao": null, "sicor_total_real_rs": null, "fogo_total_ha": 1131.22, "lotacao_bov_ha_pasto": null, "lotacao_ua_ha_pasto": 1.1799708830056064, "pct_pastagem_lulc": 21.2592, "pct_agricultura_lulc": 57.2482, "pct_natural_lulc": 12.0793, "pct_vegetacao_nativa": 0.1706}, {"ano": 1997, "lulc_area_total_ha": 186962.60065910761, "lulc_vegetacao_nativa_ha": 31171.785469079743, "lulc_pastagem_ha": 37782.34492598331, "lulc_soja_ha": 86596.65262284542, "lulc_agricultura_ha": 107825.44883120761, "lulc_mosaico_usos_ha": 9491.162850854533, "lulc_corpo_dagua_ha": 185.6082174621582, "lulc_area_urbana_ha": 213.7263086486816, "pec_bovinos_cab": 67000.0, "pec_bovinos_ua": 46900.0, "pec_suinos_cab": 5400.0, "pec_galinaceos_cab": 18000.0, "pec_ovinos_tosquiados_cab": null, "agri_soja_ton": 137000.0, "agri_milho_total_ton": 147000.0, "agri_cana_ton": null, "agri_algodao_ton": 6000.0, "agri_mandioca_ton": 1400.0, "agri_arroz_ton": 2200.0, "agri_sorgo_ton": 36000.0, "agri_feijao_ton": 15640.0, "agri_leite_mil_litros": 6500.0, "perm_cafe_total_ton": null, "perm_banana_ton": null, "perm_laranja_ton": null, "perm_manga_ton": null, "perm_mamao_ton": null, "perm_maracuja_ton": null, "perm_uva_ton": null, "pib_real_rs": null, "populacao": null, "sicor_total_real_rs": null, "fogo_total_ha": 1087.03, "lotacao_bov_ha_pasto": null, "lotacao_ua_ha_pasto": 1.2413205186676062, "pct_pastagem_lulc": 20.2085, "pct_agricultura_lulc": 57.6722, "pct_natural_lulc": 11.7783, "pct_vegetacao_nativa": 0.1667}, {"ano": 1998, "lulc_area_total_ha": 186962.60065910444, "lulc_vegetacao_nativa_ha": 30717.623500616595, "lulc_pastagem_ha": 36105.88382508542, "lulc_soja_ha": 80946.02795295196, "lulc_agricultura_ha": 108766.60371760654, "lulc_mosaico_usos_ha": 10632.27702455441, "lulc_corpo_dagua_ha": 191.3331529052733, "lulc_area_urbana_ha": 223.2897064575195, "pec_bovinos_cab": 65000.0, "pec_bovinos_ua": 45500.0, "pec_suinos_cab": 5400.0, "pec_galinaceos_cab": 18000.0, "pec_ovinos_tosquiados_cab": null, "agri_soja_ton": 196000.0, "agri_milho_total_ton": 112500.0, "agri_cana_ton": null, "agri_algodao_ton": 5950.0, "agri_mandioca_ton": 1400.0, "agri_arroz_ton": 3000.0, "agri_sorgo_ton": 30000.0, "agri_feijao_ton": 13250.0, "agri_leite_mil_litros": 6362.0, "perm_cafe_total_ton": null, "perm_banana_ton": null, "perm_laranja_ton": null, "perm_manga_ton": null, "perm_mamao_ton": null, "perm_maracuja_ton": null, "perm_uva_ton": null, "pib_real_rs": null, "populacao": null, "sicor_total_real_rs": null, "fogo_total_ha": 1574.05, "lotacao_bov_ha_pasto": null, "lotacao_ua_ha_pasto": 1.2601824184785029, "pct_pastagem_lulc": 19.3118, "pct_agricultura_lulc": 58.1756, "pct_natural_lulc": 11.6419, "pct_vegetacao_nativa": 0.1643}, {"ano": 1999, "lulc_area_total_ha": 186962.60065910884, "lulc_vegetacao_nativa_ha": 30597.945413842852, "lulc_pastagem_ha": 33874.20240353391, "lulc_soja_ha": 96949.4541720176, "lulc_agricultura_ha": 112160.13529587633, "lulc_mosaico_usos_ha": 9508.41015134891, "lulc_corpo_dagua_ha": 201.1548247619627, "lulc_area_urbana_ha": 228.2423841857912, "pec_bovinos_cab": 65000.0, "pec_bovinos_ua": 45500.0, "pec_suinos_cab": 5400.0, "pec_galinaceos_cab": 18000.0, "pec_ovinos_tosquiados_cab": null, "agri_soja_ton": 169200.0, "agri_milho_total_ton": 167950.0, "agri_cana_ton": null, "agri_algodao_ton": 1380.0, "agri_mandioca_ton": 1400.0, "agri_arroz_ton": 8910.0, "agri_sorgo_ton": 12000.0, "agri_feijao_ton": 9120.0, "agri_leite_mil_litros": 6362.0, "perm_cafe_total_ton": null, "perm_banana_ton": null, "perm_laranja_ton": null, "perm_manga_ton": null, "perm_mamao_ton": null, "perm_maracuja_ton": null, "perm_uva_ton": null, "pib_real_rs": null, "populacao": null, "sicor_total_real_rs": null, "fogo_total_ha": 2051.23, "lotacao_bov_ha_pasto": null, "lotacao_ua_ha_pasto": 1.343205057877709, "pct_pastagem_lulc": 18.1182, "pct_agricultura_lulc": 59.9907, "pct_natural_lulc": 11.7169, "pct_vegetacao_nativa": 0.1637}, {"ano": 2000, "lulc_area_total_ha": 186962.6006591114, "lulc_vegetacao_nativa_ha": 30603.73427250991, "lulc_pastagem_ha": 32708.70021815282, "lulc_soja_ha": 102066.8210048682, "lulc_agricultura_ha": 114961.43347350854, "lulc_mosaico_usos_ha": 7860.393096185238, "lulc_corpo_dagua_ha": 137.0706416015626, "lulc_area_urbana_ha": 245.9176374023441, "pec_bovinos_cab": 65000.0, "pec_bovinos_ua": 45500.0, "pec_suinos_cab": 25500.0, "pec_galinaceos_cab": 68000.0, "pec_ovinos_tosquiados_cab": null, "agri_soja_ton": 210000.0, "agri_milho_total_ton": 172500.0, "agri_cana_ton": null, "agri_algodao_ton": 1398.0, "agri_mandioca_ton": 1400.0, "agri_arroz_ton": 3600.0, "agri_sorgo_ton": 36000.0, "agri_feijao_ton": 4400.0, "agri_leite_mil_litros": 6915.0, "perm_cafe_total_ton": null, "perm_banana_ton": null, "perm_laranja_ton": null, "perm_manga_ton": null, "perm_mamao_ton": null, "perm_maracuja_ton": null, "perm_uva_ton": null, "pib_real_rs": null, "populacao": null, "sicor_total_real_rs": null, "fogo_total_ha": 801.96, "lotacao_bov_ha_pasto": null, "lotacao_ua_ha_pasto": 1.3910671991407415, "pct_pastagem_lulc": 17.4948, "pct_agricultura_lulc": 61.489, "pct_natural_lulc": 11.7867, "pct_vegetacao_nativa": 0.1637}, {"ano": 2001, "lulc_area_total_ha": 186962.60065910374, "lulc_vegetacao_nativa_ha": 30454.707467773518, "lulc_pastagem_ha": 29552.85240148921, "lulc_soja_ha": 107428.5852436068, "lulc_agricultura_ha": 120059.03870782201, "lulc_mosaico_usos_ha": 6018.986973681589, "lulc_corpo_dagua_ha": 123.570297692871, "lulc_area_urbana_ha": 274.3510686462399, "pec_bovinos_cab": 62000.0, "pec_bovinos_ua": 43400.0, "pec_suinos_cab": 28900.0, "pec_galinaceos_cab": 73000.0, "pec_ovinos_tosquiados_cab": null, "agri_soja_ton": 224000.0, "agri_milho_total_ton": 213600.0, "agri_cana_ton": null, "agri_algodao_ton": 9600.0, "agri_mandioca_ton": 1400.0, "agri_arroz_ton": 1200.0, "agri_sorgo_ton": 14400.0, "agri_feijao_ton": 18600.0, "agri_leite_mil_litros": 6920.0, "perm_cafe_total_ton": null, "perm_banana_ton": null, "perm_laranja_ton": null, "perm_manga_ton": null, "perm_mamao_ton": null, "perm_maracuja_ton": null, "perm_uva_ton": null, "pib_real_rs": null, "populacao": 7970.0, "sicor_total_real_rs": null, "fogo_total_ha": 1651.24, "lotacao_bov_ha_pasto": null, "lotacao_ua_ha_pasto": 1.4685553668522708, "pct_pastagem_lulc": 15.8068, "pct_agricultura_lulc": 64.2155, "pct_natural_lulc": 11.8474, "pct_vegetacao_nativa": 0.1629}, {"ano": 2002, "lulc_area_total_ha": 186962.60065910456, "lulc_vegetacao_nativa_ha": 30315.694007495164, "lulc_pastagem_ha": 28025.47693310547, "lulc_soja_ha": 109344.7644954145, "lulc_agricultura_ha": 121136.22566577575, "lulc_mosaico_usos_ha": 6512.857157037249, "lulc_corpo_dagua_ha": 125.9635073486328, "lulc_area_urbana_ha": 291.0006869079584, "pec_bovinos_cab": 45000.0, "pec_bovinos_ua": 31499.999999999996, "pec_suinos_cab": 47000.0, "pec_galinaceos_cab": 115000.0, "pec_ovinos_tosquiados_cab": null, "agri_soja_ton": 288000.0, "agri_milho_total_ton": 163680.0, "agri_cana_ton": null, "agri_algodao_ton": 6200.0, "agri_mandioca_ton": 1400.0, "agri_arroz_ton": 2500.0, "agri_sorgo_ton": 21000.0, "agri_feijao_ton": 13800.0, "agri_leite_mil_litros": 6470.0, "perm_cafe_total_ton": null, "perm_banana_ton": null, "perm_laranja_ton": null, "perm_manga_ton": null, "perm_mamao_ton": null, "perm_maracuja_ton": null, "perm_uva_ton": null, "pib_real_rs": 941086292.7266178, "populacao": 8186.0, "sicor_total_real_rs": null, "fogo_total_ha": 569.94, "lotacao_bov_ha_pasto": null, "lotacao_ua_ha_pasto": 1.1239773037649967, "pct_pastagem_lulc": 14.9899, "pct_agricultura_lulc": 64.7917, "pct_natural_lulc": 11.8668, "pct_vegetacao_nativa": 0.1621}, {"ano": 2003, "lulc_area_total_ha": 186962.60065910337, "lulc_vegetacao_nativa_ha": 30356.059090399274, "lulc_pastagem_ha": 27187.36735194112, "lulc_soja_ha": 97097.26065349362, "lulc_agricultura_ha": 121287.59116524331, "lulc_mosaico_usos_ha": 7124.21473829333, "lulc_corpo_dagua_ha": 136.9014457763673, "lulc_area_urbana_ha": 299.8807573852537, "pec_bovinos_cab": 46000.0, "pec_bovinos_ua": 32199.999999999996, "pec_suinos_cab": 52000.0, "pec_galinaceos_cab": 64500.0, "pec_ovinos_tosquiados_cab": null, "agri_soja_ton": 320000.0, "agri_milho_total_ton": 180300.0, "agri_cana_ton": null, "agri_algodao_ton": 8680.0, "agri_mandioca_ton": 1400.0, "agri_arroz_ton": 2800.0, "agri_sorgo_ton": 81000.0, "agri_feijao_ton": 16500.0, "agri_leite_mil_litros": 7278.0, "perm_cafe_total_ton": null, "perm_banana_ton": null, "perm_laranja_ton": null, "perm_manga_ton": null, "perm_mamao_ton": null, "perm_maracuja_ton": null, "perm_uva_ton": null, "pib_real_rs": 777530856.9339855, "populacao": 8396.0, "sicor_total_real_rs": null, "fogo_total_ha": 365.85, "lotacao_bov_ha_pasto": null, "lotacao_ua_ha_pasto": 1.1843735946614553, "pct_pastagem_lulc": 14.5416, "pct_agricultura_lulc": 64.8726, "pct_natural_lulc": 11.9746, "pct_vegetacao_nativa": 0.1624}, {"ano": 2004, "lulc_area_total_ha": 186962.6006591088, "lulc_vegetacao_nativa_ha": 30232.068285302845, "lulc_pastagem_ha": 22354.38476582632, "lulc_soja_ha": 114813.6327379479, "lulc_agricultura_ha": 126639.52282801754, "lulc_mosaico_usos_ha": 6763.555070403994, "lulc_corpo_dagua_ha": 136.2192926818847, "lulc_area_urbana_ha": 305.2598094421385, "pec_bovinos_cab": 41000.0, "pec_bovinos_ua": 28699.999999999996, "pec_suinos_cab": 40000.0, "pec_galinaceos_cab": 63400.0, "pec_ovinos_tosquiados_cab": null, "agri_soja_ton": 280000.0, "agri_milho_total_ton": 105000.0, "agri_cana_ton": null, "agri_algodao_ton": 17501.0, "agri_mandioca_ton": 1400.0, "agri_arroz_ton": 2800.0, "agri_sorgo_ton": 90000.0, "agri_feijao_ton": 5974.0, "agri_leite_mil_litros": 6955.0, "perm_cafe_total_ton": null, "perm_banana_ton": null, "perm_laranja_ton": 968.0, "perm_manga_ton": null, "perm_mamao_ton": null, "perm_maracuja_ton": null, "perm_uva_ton": null, "pib_real_rs": 716569809.369201, "populacao": 8834.0, "sicor_total_real_rs": null, "fogo_total_ha": 449.98, "lotacao_bov_ha_pasto": null, "lotacao_ua_ha_pasto": 1.283864454363082, "pct_pastagem_lulc": 11.9566, "pct_agricultura_lulc": 67.7352, "pct_natural_lulc": 11.98, "pct_vegetacao_nativa": 0.1617}, {"ano": 2005, "lulc_area_total_ha": 186962.60065910732, "lulc_vegetacao_nativa_ha": 30184.89191217053, "lulc_pastagem_ha": 21855.51458959358, "lulc_soja_ha": 108460.8615405767, "lulc_agricultura_ha": 126891.04727075272, "lulc_mosaico_usos_ha": 7007.328456848055, "lulc_corpo_dagua_ha": 136.3046235839844, "lulc_area_urbana_ha": 315.4199375305175, "pec_bovinos_cab": 43000.0, "pec_bovinos_ua": 30099.999999999996, "pec_suinos_cab": 40000.0, "pec_galinaceos_cab": 62300.0, "pec_ovinos_tosquiados_cab": null, "agri_soja_ton": 324800.0, "agri_milho_total_ton": 129600.0, "agri_cana_ton": null, "agri_algodao_ton": 12968.0, "agri_mandioca_ton": 1040.0, "agri_arroz_ton": 1500.0, "agri_sorgo_ton": 54000.0, "agri_feijao_ton": 2280.0, "agri_leite_mil_litros": 7000.0, "perm_cafe_total_ton": null, "perm_banana_ton": null, "perm_laranja_ton": 900.0, "perm_manga_ton": null, "perm_mamao_ton": null, "perm_maracuja_ton": null, "perm_uva_ton": null, "pib_real_rs": 560902738.0776019, "populacao": 9077.0, "sicor_total_real_rs": null, "fogo_total_ha": 663.62, "lotacao_bov_ha_pasto": null, "lotacao_ua_ha_pasto": 1.3772267807563772, "pct_pastagem_lulc": 11.6898, "pct_agricultura_lulc": 67.8697, "pct_natural_lulc": 12.0187, "pct_vegetacao_nativa": 0.1614}, {"ano": 2006, "lulc_area_total_ha": 186962.60065911093, "lulc_vegetacao_nativa_ha": 30133.339719891577, "lulc_pastagem_ha": 20462.07399240119, "lulc_soja_ha": 120938.7402970563, "lulc_agricultura_ha": 129105.0631713849, "lulc_mosaico_usos_ha": 6227.119157897892, "lulc_corpo_dagua_ha": 139.1262077209472, "lulc_area_urbana_ha": 321.2254531127929, "pec_bovinos_cab": 45000.0, "pec_bovinos_ua": 31499.999999999996, "pec_suinos_cab": 39100.0, "pec_galinaceos_cab": 62700.0, "pec_ovinos_tosquiados_cab": null, "agri_soja_ton": 252000.0, "agri_milho_total_ton": 109200.0, "agri_cana_ton": null, "agri_algodao_ton": 11520.0, "agri_mandioca_ton": 980.0, "agri_arroz_ton": 1200.0, "agri_sorgo_ton": 27000.0, "agri_feijao_ton": 4800.0, "agri_leite_mil_litros": 7320.0, "perm_cafe_total_ton": null, "perm_banana_ton": null, "perm_laranja_ton": 900.0, "perm_manga_ton": null, "perm_mamao_ton": null, "perm_maracuja_ton": null, "perm_uva_ton": null, "pib_real_rs": 456451531.9954444, "populacao": 9318.0, "sicor_total_real_rs": null, "fogo_total_ha": 463.5, "lotacao_bov_ha_pasto": null, "lotacao_ua_ha_pasto": 1.5394333932961957, "pct_pastagem_lulc": 10.9445, "pct_agricultura_lulc": 69.054, "pct_natural_lulc": 12.0707, "pct_vegetacao_nativa": 0.1612}, {"ano": 2007, "lulc_area_total_ha": 186962.60065911195, "lulc_vegetacao_nativa_ha": 29898.490103674496, "lulc_pastagem_ha": 20331.88109594127, "lulc_soja_ha": 119256.4075542961, "lulc_agricultura_ha": 129440.11885634069, "lulc_mosaico_usos_ha": 6241.294414800991, "lulc_corpo_dagua_ha": 148.4473165649414, "lulc_area_urbana_ha": 330.6197447021483, "pec_bovinos_cab": 42250.0, "pec_bovinos_ua": 29574.999999999996, "pec_suinos_cab": 28000.0, "pec_galinaceos_cab": 62700.0, "pec_ovinos_tosquiados_cab": null, "agri_soja_ton": 249200.0, "agri_milho_total_ton": 88000.0, "agri_cana_ton": null, "agri_algodao_ton": 25506.0, "agri_mandioca_ton": 980.0, "agri_arroz_ton": 2400.0, "agri_sorgo_ton": 20000.0, "agri_feijao_ton": 2520.0, "agri_leite_mil_litros": 6850.0, "perm_cafe_total_ton": null, "perm_banana_ton": null, "perm_laranja_ton": 900.0, "perm_manga_ton": null, "perm_mamao_ton": null, "perm_maracuja_ton": null, "perm_uva_ton": null, "pib_real_rs": 547645397.8076372, "populacao": null, "sicor_total_real_rs": null, "fogo_total_ha": 1569.06, "lotacao_bov_ha_pasto": null, "lotacao_ua_ha_pasto": 1.45461208731463, "pct_pastagem_lulc": 10.8748, "pct_agricultura_lulc": 69.2332, "pct_natural_lulc": 11.9908, "pct_vegetacao_nativa": 0.1599}, {"ano": 2008, "lulc_area_total_ha": 186962.60065911396, "lulc_vegetacao_nativa_ha": 29833.476307977366, "lulc_pastagem_ha": 19761.03036046166, "lulc_soja_ha": 110638.7883330757, "lulc_agricultura_ha": 129696.29406674312, "lulc_mosaico_usos_ha": 6611.230972100766, "lulc_corpo_dagua_ha": 150.9286536315917, "lulc_area_urbana_ha": 335.9990349304198, "pec_bovinos_cab": 52000.0, "pec_bovinos_ua": 36400.0, "pec_suinos_cab": 28600.0, "pec_galinaceos_cab": 61200.0, "pec_ovinos_tosquiados_cab": null, "agri_soja_ton": 303600.0, "agri_milho_total_ton": 225000.0, "agri_cana_ton": 320000.0, "agri_algodao_ton": 33750.0, "agri_mandioca_ton": 980.0, "agri_arroz_ton": 240.0, "agri_sorgo_ton": 39200.0, "agri_feijao_ton": 5450.0, "agri_leite_mil_litros": 8430.0, "perm_cafe_total_ton": null, "perm_banana_ton": null, "perm_laranja_ton": 990.0, "perm_manga_ton": null, "perm_mamao_ton": null, "perm_maracuja_ton": null, "perm_uva_ton": null, "pib_real_rs": 777175865.3227612, "populacao": 9766.0, "sicor_total_real_rs": null, "fogo_total_ha": 475.48, "lotacao_bov_ha_pasto": null, "lotacao_ua_ha_pasto": 1.8420092138935218, "pct_pastagem_lulc": 10.5695, "pct_agricultura_lulc": 69.3702, "pct_natural_lulc": 12.0121, "pct_vegetacao_nativa": 0.1596}, {"ano": 2009, "lulc_area_total_ha": 186962.60065911093, "lulc_vegetacao_nativa_ha": 29752.200867675874, "lulc_pastagem_ha": 18877.37619815692, "lulc_soja_ha": 114930.337508244, "lulc_agricultura_ha": 130095.7980702924, "lulc_mosaico_usos_ha": 7174.432233386132, "lulc_corpo_dagua_ha": 147.5973485717772, "lulc_area_urbana_ha": 340.4392142150876, "pec_bovinos_cab": 53000.0, "pec_bovinos_ua": 37100.0, "pec_suinos_cab": 49000.0, "pec_galinaceos_cab": 504300.0, "pec_ovinos_tosquiados_cab": null, "agri_soja_ton": 304000.0, "agri_milho_total_ton": 257250.0, "agri_cana_ton": 725200.0, "agri_algodao_ton": 18228.0, "agri_mandioca_ton": 980.0, "agri_arroz_ton": 450.0, "agri_sorgo_ton": 58000.0, "agri_feijao_ton": 7950.0, "agri_leite_mil_litros": 8750.0, "perm_cafe_total_ton": null, "perm_banana_ton": null, "perm_laranja_ton": 990.0, "perm_manga_ton": null, "perm_mamao_ton": null, "perm_maracuja_ton": null, "perm_uva_ton": null, "pib_real_rs": 940667123.7074847, "populacao": 9965.0, "sicor_total_real_rs": null, "fogo_total_ha": 871.1, "lotacao_bov_ha_pasto": null, "lotacao_ua_ha_pasto": 1.9653154977979532, "pct_pastagem_lulc": 10.0969, "pct_agricultura_lulc": 69.5839, "pct_natural_lulc": 12.0104, "pct_vegetacao_nativa": 0.1591}, {"ano": 2010, "lulc_area_total_ha": 186962.60065911224, "lulc_vegetacao_nativa_ha": 29734.17512561677, "lulc_pastagem_ha": 17981.76166095593, "lulc_soja_ha": 115926.724195678, "lulc_agricultura_ha": 130675.53434039855, "lulc_mosaico_usos_ha": 7543.626115454002, "lulc_corpo_dagua_ha": 140.0760756958008, "lulc_area_urbana_ha": 354.2715237121579, "pec_bovinos_cab": 50600.0, "pec_bovinos_ua": 35420.0, "pec_suinos_cab": 44880.0, "pec_galinaceos_cab": 39700.0, "pec_ovinos_tosquiados_cab": null, "agri_soja_ton": 303000.0, "agri_milho_total_ton": 321900.0, "agri_cana_ton": 1150000.0, "agri_algodao_ton": 13920.0, "agri_mandioca_ton": 980.0, "agri_arroz_ton": null, "agri_sorgo_ton": 24000.0, "agri_feijao_ton": 5420.0, "agri_leite_mil_litros": 8490.0, "perm_cafe_total_ton": null, "perm_banana_ton": null, "perm_laranja_ton": 990.0, "perm_manga_ton": null, "perm_mamao_ton": null, "perm_maracuja_ton": null, "perm_uva_ton": null, "pib_real_rs": 855848257.8734705, "populacao": null, "sicor_total_real_rs": null, "fogo_total_ha": 1475.17, "lotacao_bov_ha_pasto": null, "lotacao_ua_ha_pasto": 1.969773633298009, "pct_pastagem_lulc": 9.6178, "pct_agricultura_lulc": 69.8939, "pct_natural_lulc": 12.078, "pct_vegetacao_nativa": 0.159}, {"ano": 2011, "lulc_area_total_ha": 186962.6006591163, "lulc_vegetacao_nativa_ha": 29896.552774341137, "lulc_pastagem_ha": 17041.11393989858, "lulc_soja_ha": 117219.1501791662, "lulc_agricultura_ha": 130915.71062088374, "lulc_mosaico_usos_ha": 8104.543642620774, "lulc_corpo_dagua_ha": 133.6642632995606, "lulc_area_urbana_ha": 369.5552664550777, "pec_bovinos_cab": 51000.0, "pec_bovinos_ua": 35700.0, "pec_suinos_cab": 48050.0, "pec_galinaceos_cab": 94500.0, "pec_ovinos_tosquiados_cab": null, "agri_soja_ton": 356400.0, "agri_milho_total_ton": 430800.0, "agri_cana_ton": 860000.0, "agri_algodao_ton": 42543.0, "agri_mandioca_ton": 1050.0, "agri_arroz_ton": 150.0, "agri_sorgo_ton": 19600.0, "agri_feijao_ton": 2400.0, "agri_leite_mil_litros": 8570.0, "perm_cafe_total_ton": null, "perm_banana_ton": null, "perm_laranja_ton": 1125.0, "perm_manga_ton": null, "perm_mamao_ton": null, "perm_maracuja_ton": null, "perm_uva_ton": null, "pib_real_rs": 1060234203.8173245, "populacao": 10790.0, "sicor_total_real_rs": null, "fogo_total_ha": 380.27, "lotacao_bov_ha_pasto": null, "lotacao_ua_ha_pasto": 2.094933472419026, "pct_pastagem_lulc": 9.1147, "pct_agricultura_lulc": 70.0224, "pct_natural_lulc": 12.2297, "pct_vegetacao_nativa": 0.1599}, {"ano": 2012, "lulc_area_total_ha": 186962.6006591201, "lulc_vegetacao_nativa_ha": 30029.306068463426, "lulc_pastagem_ha": 15667.90467928474, "lulc_soja_ha": 120842.3750083447, "lulc_agricultura_ha": 131793.0391357861, "lulc_mosaico_usos_ha": 8505.694651635653, "lulc_corpo_dagua_ha": 126.2232194152832, "lulc_area_urbana_ha": 373.5685493896481, "pec_bovinos_cab": 47000.0, "pec_bovinos_ua": 32900.0, "pec_suinos_cab": 48170.0, "pec_galinaceos_cab": 10000.0, "pec_ovinos_tosquiados_cab": null, "agri_soja_ton": 368880.0, "agri_milho_total_ton": 489000.0, "agri_cana_ton": 407430.0, "agri_algodao_ton": 29335.0, "agri_mandioca_ton": 480.0, "agri_arroz_ton": null, "agri_sorgo_ton": 15000.0, "agri_feijao_ton": 5850.0, "agri_leite_mil_litros": 8550.0, "perm_cafe_total_ton": null, "perm_banana_ton": null, "perm_laranja_ton": 1130.0, "perm_manga_ton": null, "perm_mamao_ton": null, "perm_maracuja_ton": null, "perm_uva_ton": null, "pib_real_rs": 1170990022.202616, "populacao": 11001.0, "sicor_total_real_rs": null, "fogo_total_ha": 585.0, "lotacao_bov_ha_pasto": null, "lotacao_ua_ha_pasto": 2.099834066740182, "pct_pastagem_lulc": 8.3802, "pct_agricultura_lulc": 70.4917, "pct_natural_lulc": 12.3413, "pct_vegetacao_nativa": 0.1606}, {"ano": 2013, "lulc_area_total_ha": 186962.6006591146, "lulc_vegetacao_nativa_ha": 30056.761282452568, "lulc_pastagem_ha": 15233.87236521603, "lulc_soja_ha": 120474.9386168294, "lulc_agricultura_ha": 132318.633827126, "lulc_mosaico_usos_ha": 8376.614514623956, "lulc_corpo_dagua_ha": 117.0779410583495, "lulc_area_urbana_ha": 394.6584329406734, "pec_bovinos_cab": 43000.0, "pec_bovinos_ua": 30099.999999999996, "pec_suinos_cab": 48000.0, "pec_galinaceos_cab": 9500.0, "pec_ovinos_tosquiados_cab": null, "agri_soja_ton": 396000.0, "agri_milho_total_ton": 487140.0, "agri_cana_ton": 453220.0, "agri_algodao_ton": 16578.0, "agri_mandioca_ton": 620.0, "agri_arroz_ton": null, "agri_sorgo_ton": 21000.0, "agri_feijao_ton": 3630.0, "agri_leite_mil_litros": 7820.0, "perm_cafe_total_ton": null, "perm_banana_ton": null, "perm_laranja_ton": 1130.0, "perm_manga_ton": null, "perm_mamao_ton": null, "perm_maracuja_ton": null, "perm_uva_ton": null, "pib_real_rs": 1196414482.9096284, "populacao": 11611.0, "sicor_total_real_rs": 379997933.5247416, "fogo_total_ha": 1080.72, "lotacao_bov_ha_pasto": null, "lotacao_ua_ha_pasto": 1.9758600622602205, "pct_pastagem_lulc": 8.1481, "pct_agricultura_lulc": 70.7728, "pct_natural_lulc": 12.3784, "pct_vegetacao_nativa": 0.1608}, {"ano": 2014, "lulc_area_total_ha": 186962.60065910974, "lulc_vegetacao_nativa_ha": 29947.623460931587, "lulc_pastagem_ha": 14727.19456441044, "lulc_soja_ha": 121517.6921978365, "lulc_agricultura_ha": 133786.81639160472, "lulc_mosaico_usos_ha": 7540.331225152488, "lulc_corpo_dagua_ha": 113.1467873779296, "lulc_area_urbana_ha": 398.1593831237789, "pec_bovinos_cab": 44000.0, "pec_bovinos_ua": 30799.999999999996, "pec_suinos_cab": 47800.0, "pec_galinaceos_cab": 9000.0, "pec_ovinos_tosquiados_cab": null, "agri_soja_ton": 338800.0, "agri_milho_total_ton": 627300.0, "agri_cana_ton": 604500.0, "agri_algodao_ton": 19260.0, "agri_mandioca_ton": 800.0, "agri_arroz_ton": null, "agri_sorgo_ton": 15500.0, "agri_feijao_ton": 3150.0, "agri_leite_mil_litros": 12200.0, "perm_cafe_total_ton": null, "perm_banana_ton": null, "perm_laranja_ton": 1100.0, "perm_manga_ton": null, "perm_mamao_ton": null, "perm_maracuja_ton": null, "perm_uva_ton": null, "pib_real_rs": 1028531938.2381359, "populacao": 11858.0, "sicor_total_real_rs": 378996233.6667818, "fogo_total_ha": 2220.08, "lotacao_bov_ha_pasto": null, "lotacao_ua_ha_pasto": 2.091369124329416, "pct_pastagem_lulc": 7.8771, "pct_agricultura_lulc": 71.5581, "pct_natural_lulc": 12.3446, "pct_vegetacao_nativa": 0.1602}, {"ano": 2015, "lulc_area_total_ha": 186962.60065911445, "lulc_vegetacao_nativa_ha": 29902.663571850815, "lulc_pastagem_ha": 14646.57871925663, "lulc_soja_ha": 124219.4358828326, "lulc_agricultura_ha": 134121.81901842213, "lulc_mosaico_usos_ha": 7279.234751739401, "lulc_corpo_dagua_ha": 112.7186168395995, "lulc_area_urbana_ha": 408.1509035278316, "pec_bovinos_cab": 46000.0, "pec_bovinos_ua": 32199.999999999996, "pec_suinos_cab": 70000.0, "pec_galinaceos_cab": 8500.0, "pec_ovinos_tosquiados_cab": null, "agri_soja_ton": 285000.0, "agri_milho_total_ton": 670200.0, "agri_cana_ton": 606800.0, "agri_algodao_ton": 9240.0, "agri_mandioca_ton": 930.0, "agri_arroz_ton": null, "agri_sorgo_ton": 12600.0, "agri_feijao_ton": 2970.0, "agri_leite_mil_litros": 13700.0, "perm_cafe_total_ton": null, "perm_banana_ton": null, "perm_laranja_ton": 1120.0, "perm_manga_ton": null, "perm_mamao_ton": null, "perm_maracuja_ton": null, "perm_uva_ton": null, "pib_real_rs": 921386993.7331256, "populacao": 12101.0, "sicor_total_real_rs": 296564574.71698785, "fogo_total_ha": 126.64, "lotacao_bov_ha_pasto": null, "lotacao_ua_ha_pasto": 2.198465636050893, "pct_pastagem_lulc": 7.834, "pct_agricultura_lulc": 71.7372, "pct_natural_lulc": 12.35, "pct_vegetacao_nativa": 0.1599}, {"ano": 2016, "lulc_area_total_ha": 186962.6006591023, "lulc_vegetacao_nativa_ha": 29857.531491943595, "lulc_pastagem_ha": 14506.88431074219, "lulc_soja_ha": 85315.8897233359, "lulc_agricultura_ha": 134592.63208573792, "lulc_mosaico_usos_ha": 6981.986889190568, "lulc_corpo_dagua_ha": 111.1810024291992, "lulc_area_urbana_ha": 424.5433359130876, "pec_bovinos_cab": 47000.0, "pec_bovinos_ua": 32900.0, "pec_suinos_cab": 74000.0, "pec_galinaceos_cab": 9000.0, "pec_ovinos_tosquiados_cab": null, "agri_soja_ton": 429000.0, "agri_milho_total_ton": 260760.0, "agri_cana_ton": 180000.0, "agri_algodao_ton": 6196.0, "agri_mandioca_ton": 728.0, "agri_arroz_ton": null, "agri_sorgo_ton": 3600.0, "agri_feijao_ton": 3980.0, "agri_leite_mil_litros": 10000.0, "perm_cafe_total_ton": null, "perm_banana_ton": null, "perm_laranja_ton": 900.0, "perm_manga_ton": null, "perm_mamao_ton": null, "perm_maracuja_ton": null, "perm_uva_ton": null, "pib_real_rs": 1082713067.042613, "populacao": 12337.0, "sicor_total_real_rs": 245321621.14760685, "fogo_total_ha": 281.37, "lotacao_bov_ha_pasto": null, "lotacao_ua_ha_pasto": 2.2678887688955998, "pct_pastagem_lulc": 7.7592, "pct_agricultura_lulc": 71.9891, "pct_natural_lulc": 12.3403, "pct_vegetacao_nativa": 0.1597}, {"ano": 2017, "lulc_area_total_ha": 186962.60065912516, "lulc_vegetacao_nativa_ha": 29749.128521301467, "lulc_pastagem_ha": 13844.17536031505, "lulc_soja_ha": 129875.5350699282, "lulc_agricultura_ha": 135784.775783478, "lulc_mosaico_usos_ha": 6563.012795934967, "lulc_corpo_dagua_ha": 111.9494022033691, "lulc_area_urbana_ha": 427.787896600344, "pec_bovinos_cab": 48000.0, "pec_bovinos_ua": 33600.0, "pec_suinos_cab": 112000.0, "pec_galinaceos_cab": 11000.0, "pec_ovinos_tosquiados_cab": null, "agri_soja_ton": 455880.0, "agri_milho_total_ton": 756600.0, "agri_cana_ton": 89485.0, "agri_algodao_ton": 4350.0, "agri_mandioca_ton": 728.0, "agri_arroz_ton": null, "agri_sorgo_ton": 4200.0, "agri_feijao_ton": 5160.0, "agri_leite_mil_litros": 10010.0, "perm_cafe_total_ton": null, "perm_banana_ton": null, "perm_laranja_ton": null, "perm_manga_ton": null, "perm_mamao_ton": null, "perm_maracuja_ton": null, "perm_uva_ton": null, "pib_real_rs": 1117969089.7692027, "populacao": 12566.0, "sicor_total_real_rs": 400318696.1734811, "fogo_total_ha": 206.01, "lotacao_bov_ha_pasto": null, "lotacao_ua_ha_pasto": 2.4270134641833496, "pct_pastagem_lulc": 7.4048, "pct_agricultura_lulc": 72.6267, "pct_natural_lulc": 12.3111, "pct_vegetacao_nativa": 0.1591}, {"ano": 2018, "lulc_area_total_ha": 186962.60065911652, "lulc_vegetacao_nativa_ha": 29803.682205987785, "lulc_pastagem_ha": 13415.28601351321, "lulc_soja_ha": 131178.6284730873, "lulc_agricultura_ha": 135904.6729291847, "lulc_mosaico_usos_ha": 6785.170297363207, "lulc_corpo_dagua_ha": 112.3781149780273, "lulc_area_urbana_ha": 434.5336441650418, "pec_bovinos_cab": 49500.0, "pec_bovinos_ua": 34650.0, "pec_suinos_cab": 55000.0, "pec_galinaceos_cab": 12000.0, "pec_ovinos_tosquiados_cab": null, "agri_soja_ton": 454860.0, "agri_milho_total_ton": 631080.0, "agri_cana_ton": 60000.0, "agri_algodao_ton": 11181.0, "agri_mandioca_ton": 280.0, "agri_arroz_ton": null, "agri_sorgo_ton": 23100.0, "agri_feijao_ton": 4950.0, "agri_leite_mil_litros": 9950.0, "perm_cafe_total_ton": null, "perm_banana_ton": null, "perm_laranja_ton": null, "perm_manga_ton": null, "perm_mamao_ton": null, "perm_maracuja_ton": null, "perm_uva_ton": null, "pib_real_rs": 1094975124.7962337, "populacao": 13115.0, "sicor_total_real_rs": 364261726.7421137, "fogo_total_ha": 1028.95, "lotacao_bov_ha_pasto": null, "lotacao_ua_ha_pasto": 2.5828744884825467, "pct_pastagem_lulc": 7.1754, "pct_agricultura_lulc": 72.6908, "pct_natural_lulc": 12.3553, "pct_vegetacao_nativa": 0.1594}, {"ano": 2019, "lulc_area_total_ha": 186962.600659114, "lulc_vegetacao_nativa_ha": 29834.819622937182, "lulc_pastagem_ha": 12335.17737959594, "lulc_soja_ha": 133645.7861401137, "lulc_agricultura_ha": 136495.91100084365, "lulc_mosaico_usos_ha": 7241.543529754542, "lulc_corpo_dagua_ha": 111.694555883789, "lulc_area_urbana_ha": 440.2541989257829, "pec_bovinos_cab": 42000.0, "pec_bovinos_ua": 29399.999999999996, "pec_suinos_cab": 50000.0, "pec_galinaceos_cab": 11000.0, "pec_ovinos_tosquiados_cab": null, "agri_soja_ton": 421200.0, "agri_milho_total_ton": 832080.0, "agri_cana_ton": 106000.0, "agri_algodao_ton": 19140.0, "agri_mandioca_ton": 280.0, "agri_arroz_ton": null, "agri_sorgo_ton": 9600.0, "agri_feijao_ton": 5910.0, "agri_leite_mil_litros": 8090.0, "perm_cafe_total_ton": null, "perm_banana_ton": null, "perm_laranja_ton": null, "perm_manga_ton": null, "perm_mamao_ton": null, "perm_maracuja_ton": null, "perm_uva_ton": null, "pib_real_rs": 1132546988.0791364, "populacao": 13396.0, "sicor_total_real_rs": 383999078.34066814, "fogo_total_ha": 46.53, "lotacao_bov_ha_pasto": null, "lotacao_ua_ha_pasto": 2.3834274202356904, "pct_pastagem_lulc": 6.5977, "pct_agricultura_lulc": 73.0071, "pct_natural_lulc": 12.4019, "pct_vegetacao_nativa": 0.1596}, {"ano": 2020, "lulc_area_total_ha": 186962.6006591164, "lulc_vegetacao_nativa_ha": 29780.80431796906, "lulc_pastagem_ha": 11737.17700621939, "lulc_soja_ha": 129665.8690059852, "lulc_agricultura_ha": 136230.7272075782, "lulc_mosaico_usos_ha": 8150.044970031642, "lulc_corpo_dagua_ha": 110.8393307312011, "lulc_area_urbana_ha": 455.0254478515637, "pec_bovinos_cab": 47810.0, "pec_bovinos_ua": 33467.0, "pec_suinos_cab": 43000.0, "pec_galinaceos_cab": 11500.0, "pec_ovinos_tosquiados_cab": null, "agri_soja_ton": 496800.0, "agri_milho_total_ton": 762420.0, "agri_cana_ton": 102000.0, "agri_algodao_ton": 19390.0, "agri_mandioca_ton": 280.0, "agri_arroz_ton": null, "agri_sorgo_ton": 23100.0, "agri_feijao_ton": 6710.0, "agri_leite_mil_litros": 8150.0, "perm_cafe_total_ton": null, "perm_banana_ton": null, "perm_laranja_ton": null, "perm_manga_ton": null, "perm_mamao_ton": null, "perm_maracuja_ton": null, "perm_uva_ton": null, "pib_real_rs": 1340256487.9787226, "populacao": 13672.0, "sicor_total_real_rs": 378550236.0197116, "fogo_total_ha": 209.07, "lotacao_bov_ha_pasto": null, "lotacao_ua_ha_pasto": 2.8513670691228596, "pct_pastagem_lulc": 6.2778, "pct_agricultura_lulc": 72.8652, "pct_natural_lulc": 12.413, "pct_vegetacao_nativa": 0.1593}, {"ano": 2021, "lulc_area_total_ha": 186962.6006591215, "lulc_vegetacao_nativa_ha": 29740.54622879047, "lulc_pastagem_ha": 10888.15150281365, "lulc_soja_ha": 132375.3552732999, "lulc_agricultura_ha": 136471.4348132291, "lulc_mosaico_usos_ha": 8763.091061236508, "lulc_corpo_dagua_ha": 109.2177389770507, "lulc_area_urbana_ha": 469.285500793458, "pec_bovinos_cab": 46581.0, "pec_bovinos_ua": 32606.699999999997, "pec_suinos_cab": 30980.0, "pec_galinaceos_cab": 11000.0, "pec_ovinos_tosquiados_cab": null, "agri_soja_ton": 468600.0, "agri_milho_total_ton": 757920.0, "agri_cana_ton": 85400.0, "agri_algodao_ton": 11583.0, "agri_mandioca_ton": 280.0, "agri_arroz_ton": null, "agri_sorgo_ton": 24500.0, "agri_feijao_ton": 2850.0, "agri_leite_mil_litros": 8970.0, "perm_cafe_total_ton": null, "perm_banana_ton": null, "perm_laranja_ton": null, "perm_manga_ton": null, "perm_mamao_ton": null, "perm_maracuja_ton": null, "perm_uva_ton": null, "pib_real_rs": 1861491277.9787133, "populacao": 13935.0, "sicor_total_real_rs": 528809517.5985435, "fogo_total_ha": 83.79, "lotacao_bov_ha_pasto": null, "lotacao_ua_ha_pasto": 2.99469565532533, "pct_pastagem_lulc": 5.8237, "pct_agricultura_lulc": 72.994, "pct_natural_lulc": 12.4135, "pct_vegetacao_nativa": 0.1591}, {"ano": 2022, "lulc_area_total_ha": 186962.6006591174, "lulc_vegetacao_nativa_ha": 29774.041331469933, "lulc_pastagem_ha": 9961.68505581656, "lulc_soja_ha": 133725.0781968309, "lulc_agricultura_ha": 136865.60033688217, "lulc_mosaico_usos_ha": 9232.092615264875, "lulc_corpo_dagua_ha": 114.8593595153808, "lulc_area_urbana_ha": 494.9005171447769, "pec_bovinos_cab": 48529.0, "pec_bovinos_ua": 33970.299999999996, "pec_suinos_cab": 25603.0, "pec_galinaceos_cab": 9965.0, "pec_ovinos_tosquiados_cab": null, "agri_soja_ton": 553800.0, "agri_milho_total_ton": 615920.0, "agri_cana_ton": 84980.0, "agri_algodao_ton": 12600.0, "agri_mandioca_ton": 280.0, "agri_arroz_ton": null, "agri_sorgo_ton": 7000.0, "agri_feijao_ton": 2881.0, "agri_leite_mil_litros": 10010.0, "perm_cafe_total_ton": null, "perm_banana_ton": null, "perm_laranja_ton": null, "perm_manga_ton": null, "perm_mamao_ton": null, "perm_maracuja_ton": null, "perm_uva_ton": null, "pib_real_rs": 2014380117.266156, "populacao": null, "sicor_total_real_rs": 579067047.7906854, "fogo_total_ha": 512.3, "lotacao_bov_ha_pasto": null, "lotacao_ua_ha_pasto": 3.4100957628814985, "pct_pastagem_lulc": 5.3282, "pct_agricultura_lulc": 73.2048, "pct_natural_lulc": 12.4401, "pct_vegetacao_nativa": 0.1593}, {"ano": 2023, "lulc_area_total_ha": 186962.60065912674, "lulc_vegetacao_nativa_ha": 29709.892312671152, "lulc_pastagem_ha": 9317.729035162316, "lulc_soja_ha": 134038.7780787859, "lulc_agricultura_ha": 136919.26893917404, "lulc_mosaico_usos_ha": 9862.705914007627, "lulc_corpo_dagua_ha": 133.9911796813964, "lulc_area_urbana_ha": 498.9136925964372, "pec_bovinos_cab": 47646.0, "pec_bovinos_ua": 33352.2, "pec_suinos_cab": 29670.0, "pec_galinaceos_cab": 10000.0, "pec_ovinos_tosquiados_cab": null, "agri_soja_ton": 553800.0, "agri_milho_total_ton": 982050.0, "agri_cana_ton": 89600.0, "agri_algodao_ton": 4140.0, "agri_mandioca_ton": 280.0, "agri_arroz_ton": null, "agri_sorgo_ton": 3600.0, "agri_feijao_ton": 3321.0, "agri_leite_mil_litros": 17934.0, "perm_cafe_total_ton": null, "perm_banana_ton": null, "perm_laranja_ton": null, "perm_manga_ton": null, "perm_mamao_ton": null, "perm_maracuja_ton": null, "perm_uva_ton": null, "pib_real_rs": 1698098213.441901, "populacao": null, "sicor_total_real_rs": 510511788.896387, "fogo_total_ha": 174.51, "lotacao_bov_ha_pasto": null, "lotacao_ua_ha_pasto": 3.5794344173498494, "pct_pastagem_lulc": 4.9837, "pct_agricultura_lulc": 73.2335, "pct_natural_lulc": 12.4194, "pct_vegetacao_nativa": 0.1589}, {"ano": 2024, "lulc_area_total_ha": 186962.6006591263, "lulc_vegetacao_nativa_ha": 29607.075653424312, "lulc_pastagem_ha": 8566.037124578874, "lulc_soja_ha": 135290.942681532, "lulc_agricultura_ha": 137124.84062153441, "lulc_mosaico_usos_ha": 10530.2687870545, "lulc_corpo_dagua_ha": 139.6290034423828, "lulc_area_urbana_ha": 501.902226696779, "pec_bovinos_cab": 43091.0, "pec_bovinos_ua": 30163.699999999997, "pec_suinos_cab": 49507.0, "pec_galinaceos_cab": 6100.0, "pec_ovinos_tosquiados_cab": null, "agri_soja_ton": 523300.0, "agri_milho_total_ton": 636220.0, "agri_cana_ton": 91000.0, "agri_algodao_ton": 6240.0, "agri_mandioca_ton": 290.0, "agri_arroz_ton": 2112.0, "agri_sorgo_ton": 49500.0, "agri_feijao_ton": 2920.0, "agri_leite_mil_litros": 20100.0, "perm_cafe_total_ton": null, "perm_banana_ton": null, "perm_laranja_ton": null, "perm_manga_ton": null, "perm_mamao_ton": null, "perm_maracuja_ton": null, "perm_uva_ton": null, "pib_real_rs": null, "populacao": 12957.0, "sicor_total_real_rs": 329350119.26, "fogo_total_ha": 2582.71, "lotacao_bov_ha_pasto": null, "lotacao_ua_ha_pasto": 3.5213132468746933, "pct_pastagem_lulc": 4.5817, "pct_agricultura_lulc": 73.3435, "pct_natural_lulc": 12.3649, "pct_vegetacao_nativa": 0.1584}]}